Workbook
Name _DLX1.CDN: #REF!
Name _DLX1.CDN: #REF!
Name BoxPlot: "BoxPlot"
Name Bubble: "Bubble"
Name Candlestick: "Candlestick"
Name Chart: "Chart"
Name ChartImage: "ChartImage"
Name ColumnRange: "ColumnRange"
Name Dumbbell: "Dumbbell"
Name Heatmap: "Heatmap"
Name Histogram: "Histogram"
Name Map: "Map"
Name OHLC: "OHLC"
Name PieChart: "PieChart"
Name Scatter: "Scatter"
Name Series: "Series"
Name Stripe: "Stripe"
Name Table: "Table"
Name TreeMap: "TreeMap"
Name Waterfall: "Waterfall"

Sheet Settings
A1: Parameters | B1: Value
A2: Start year | B2: 1993
A3: End year | B3: =YEAR(NOW())+1 -> 2027
A4: Quarterly data | B4: =COUNTA(InfoQ!A:A) -> 4
A5: Monthly data | B5: =COUNTA(InfoM!A:A) -> 12

Sheet InfoQ
A1: Indicator Code | B1: Series Name | C1: Freq | D1: Unit | E1: Source | F1: Compiled by | G1: INCLUDED | H1: Months lag | I1: Days lag | J1: log | K1: QoQ | L1: YoY
A2: RGDP_level | B2: Gross Domestic Product: SNA 2008: 2010p | C2: Q | D2: IDR bn | E2: Statistics Indonesia | F2: CEIC | G2: 0 | H2: 2 | I2: 5 | J2: 0 | K2: 0 | L2: 0
A3: RGDP_growth | B3: GDP growth | C3: Q | D3: % | E3: Statistics Indonesia | F3: CEIC | G3: 1 | H3: 2 | I3: 5 | J3: 0 | K3: 0 | L3: 0
A4: Bus_Act | B4: Business Survey: Business Activity: R: Weighted Net Balance | C4: Q | D4: % | E4: Bank Indonesia | F4: CEIC | G4: 1 | H4: 1 | I4: 17 | J4: 0 | K4: 0 | L4: 0

Sheet QuarterlyData
A1: {=TRANSPOSE(INDIRECT("InfoQ!A1:A" & Settings!$B$4))} -> Indicator Code | B1: RGDP_level | C1: RGDP_growth | D1: Bus_Act
A2: =DATE(Settings!$B$2,3,1) -> 34029 | B2: 804188.2
A3: =DATE(YEAR(A2),MONTH(A2)+3,1) -> 34121 | B3: 812901.69
A4: =DATE(YEAR(A3),MONTH(A3)+3,1) -> 34213 | B4: 873050.39
A5: =DATE(YEAR(A4),MONTH(A4)+3,1) -> 34304 | B5: 886951.14
A6: =DATE(YEAR(A5),MONTH(A5)+3,1) -> 34394 | B6: 876642.78 | C6: 9.0096543
A7: =DATE(YEAR(A6),MONTH(A6)+3,1) -> 34486 | B7: 900024.04 | C7: 10.717452
A8: =DATE(YEAR(A7),MONTH(A7)+3,1) -> 34578 | B8: 933356.07 | C8: 6.9074684
A9: =DATE(YEAR(A8),MONTH(A8)+3,1) -> 34669 | B9: 921699.23 | C9: 3.9177006
A10: =DATE(YEAR(A9),MONTH(A9)+3,1) -> 34759 | B10: 947897.67 | C10: 8.1281562
A11: =DATE(YEAR(A10),MONTH(A10)+3,1) -> 34851 | B11: 966099.26 | C11: 7.3414945
A12: =DATE(YEAR(A11),MONTH(A11)+3,1) -> 34943 | B12: 1006583.3 | C12: 7.8455833
A13: =DATE(YEAR(A12),MONTH(A12)+3,1) -> 35034 | B13: 1009670.8 | C13: 9.5445016
A14: =DATE(YEAR(A13),MONTH(A13)+3,1) -> 35125 | B14: 1002293.5 | C14: 5.738578
A15: =DATE(YEAR(A14),MONTH(A14)+3,1) -> 35217 | B15: 1030557.5 | C15: 6.672009
A16: =DATE(YEAR(A15),MONTH(A15)+3,1) -> 35309 | B16: 1091255.4 | C16: 8.4118311
A17: =DATE(YEAR(A16),MONTH(A16)+3,1) -> 35400 | B17: 1113420.1 | C17: 10.275551
... A29: =DATE(YEAR(A28),MONTH(A28)+3,1) -> 36495 | B29: 969306.6 | C29: 5.3589079
A30: =DATE(YEAR(A29),MONTH(A29)+3,1) -> 36586 | B30: 1006079.1 | C30: 4.1044027 | D30: 2.4006885
A31: =DATE(YEAR(A30),MONTH(A30)+3,1) -> 36678 | B31: 1000247.8 | C31: 4.5906774 | D31: 16.884622
A32: =DATE(YEAR(A31),MONTH(A31)+3,1) -> 36770 | B32: 1042575 | C32: 5.0221067 | D32: 20.67558
A33: =DATE(YEAR(A32),MONTH(A32)+3,1) -> 36861 | B33: 1029291.7 | C33: 6.1884575 | D33: 17.688524
A34: =DATE(YEAR(A33),MONTH(A33)+3,1) -> 36951 | B34: 1044997.1 | C34: 3.8682827 | D34: 2.8215196
A35: =DATE(YEAR(A34),MONTH(A34)+3,1) -> 37043 | B35: 1057961.8 | C35: 5.7699642 | D35: 18.643691
A36: =DATE(YEAR(A35),MONTH(A35)+3,1) -> 37135 | B36: 1078457.1 | C36: 3.4416722 | D36: 13.080204
A37: =DATE(YEAR(A36),MONTH(A36)+3,1) -> 37226 | B37: 1045365.4 | C37: 1.5616251 | D37: 10.155509
A38: =DATE(YEAR(A37),MONTH(A37)+3,1) -> 37316 | B38: 1081781.8 | C38: 3.5200718 | D38: -8.4736428
A39: =DATE(YEAR(A38),MONTH(A38)+3,1) -> 37408 | B39: 1102529.7 | C39: 4.2126241 | D39: 11.925476
A40: =DATE(YEAR(A39),MONTH(A39)+3,1) -> 37500 | B40: 1138326.1 | C40: 5.5513562 | D40: 11.902423
A41: =DATE(YEAR(A40),MONTH(A40)+3,1) -> 37591 | B41: 1094326.8 | C41: 4.6836631 | D41: -0.50889253
... A132: =DATE(YEAR(A131),MONTH(A131)+3,1) -> 45901 | B132: 3444756.7 | C132: 5.0387683 | D132: 11.551631
A133: =DATE(YEAR(A132),MONTH(A132)+3,1) -> 45992 | B133: 3474461.2 | C133: =B133/B129*100-100 -> 5.390762 | D133: 10.61
A134: =DATE(YEAR(A133),MONTH(A133)+3,1) -> 46082 | B134: 3447682.8 | C134: =B134/B130*100-100 -> 5.6102683
A135: =DATE(YEAR(A134),MONTH(A134)+3,1) -> 46174
A136: =DATE(YEAR(A135),MONTH(A135)+3,1) -> 46266
A137: =DATE(YEAR(A136),MONTH(A136)+3,1) -> 46357

Sheet InfoM
A1: Indicator Code | B1: Series Name | C1: Freq | D1: Unit | E1: Source | F1: Compiled by | G1: INCLUDED | H1: Months lag | I1: Days lag | J1: log | K1: MoM | L1: YoY
A2: Man_PMI_EM | B2: Manufacturing PMI: Headline: sa: Emerging Markets | C2: M | D2: index | E2: S&P Global | F2: CEIC | G2: 1 | H2: 1 | I2: 1 | J2: 0 | K2: 0 | L2: 0
A3: M2 | B3: Broad Money (M2) | C3: M | D3: IDR bn | E3: Bank Indonesia | F3: CEIC | G3: 1 | H3: 1 | I3: 21 | J3: 1 | K3: 0 | L3: 1
A4: Car_sales | B4: Motor Vehicle Sales: PT Astra: Local | C4: M | D4: Unit | E4: PT Astra International Tbk | F4: CEIC | G4: 1 | H4: 1 | I4: 15 | J4: 1 | K4: 0 | L4: 1
A5: Cement | B5: Consumption: Cement: Domestic | C5: M | D5: Ton th | E5: Indonesia Cement Association | F5: CEIC | G5: 1 | H5: 1 | I5: 26 | J5: 1 | K5: 0 | L5: 1
A6: Export | B6: Export: fob | C6: M | D6: USD mn | E6: Statistics Indonesia | F6: CEIC | G6: 1 | H6: 2 | I6: 1 | J6: 1 | K6: 0 | L6: 1
A7: M_con_goods | B7: Imports: Consumer Goods (CG) | C7: M | D7: USD mn | E7: Statistics Indonesia | F7: CEIC | G7: 1 | H7: 2 | I7: 1 | J7: 1 | K7: 0 | L7: 1
A8: M_cap_goods | B8: Imports: Capital Goods | C8: M | D8: USD mn | E8: Statistics Indonesia | F8: CEIC | G8: 1 | H8: 2 | I8: 1 | J8: 1 | K8: 0 | L8: 1
A9: M_raw_mat | B9: Imports: Intermediate Goods (IG) | C9: M | D9: USD mn | E9: Statistics Indonesia | F9: CEIC | G9: 1 | H9: 2 | I9: 1 | J9: 1 | K9: 0 | L9: 1
A10: Inflation | B10: Headline Inflation | C10: M | D10: % | E10: Statistics Indonesia | F10: CEIC | G10: 1 | H10: 1 | I10: 1 | J10: 0 | K10: 0 | L10: 0
A11: Forex | B11: Spot FX Rate: Month-End: Bank Indonesia: IDR to US Dollar | C11: M | D11: USD/IDR | E11: Bank Indonesia | F11: CEIC | G11: 0 | H11: 1 | I11: 1 | J11: 0 | K11: 0 | L11: 0
A12: Policy_rate | B12: Policy Rate: Month End: Indonesia: BI-Rate | C12: M | D12: % pa | E12: Bank Indonesia | F12: CEIC | G12: 1 | H12: 1 | I12: 18 | J12: 0 | K12: 0 | L12: 0

Sheet MonthlyData
A1: {=TRANSPOSE(INDIRECT("InfoM!A1:A" & Settings!$B$5))} -> Indicator Code | B1: Man_PMI_EM | C1: M2 | D1: Car_sales | E1: Cement | F1: Export | G1: M_con_goods | H1: M_cap_goods | I1: M_raw_mat | J1: Inflation | K1: Forex | L1: Policy_rate
A2: =DATE(Settings!$B$2,1,1) -> 33970 | C2: 119150 | D2: 12196 | F2: 3001.9 | K2: 2065
A3: =DATE(YEAR(A2),MONTH(A2)+1,1) -> 34001 | C3: 121123 | D3: 14265 | F3: 2892.5 | K3: 2067
A4: =DATE(YEAR(A3),MONTH(A3)+1,1) -> 34029 | C4: 123161 | D4: 13569 | F4: 3008.5 | K4: 2071
A5: =DATE(YEAR(A4),MONTH(A4)+1,1) -> 34060 | C5: 122890 | D5: 15485 | F5: 2957.5 | K5: 2079.5
A6: =DATE(YEAR(A5),MONTH(A5)+1,1) -> 34090 | C6: 123448 | D6: 16025 | F6: 3118 | K6: 2081.375
A7: =DATE(YEAR(A6),MONTH(A6)+1,1) -> 34121 | C7: 124340 | D7: 16716 | F7: 2981.2 | K7: 2089
A8: =DATE(YEAR(A7),MONTH(A7)+1,1) -> 34151 | C8: 127189 | D8: 18045 | F8: 3025.7 | K8: 2096
A9: =DATE(YEAR(A8),MONTH(A8)+1,1) -> 34182 | C9: 132531 | D9: 19846 | F9: 3128.4 | K9: 2102
A10: =DATE(YEAR(A9),MONTH(A9)+1,1) -> 34213 | C10: 136387 | D10: 19830 | F10: 3084.1 | K10: 2106.5
A11: =DATE(YEAR(A10),MONTH(A10)+1,1) -> 34243 | C11: 138460 | D11: 20159 | F11: 3218.4 | K11: 2101.55
A12: =DATE(YEAR(A11),MONTH(A11)+1,1) -> 34274 | C12: 141304 | D12: 22390 | F12: 3212.1 | K12: 2103.35
A13: =DATE(YEAR(A12),MONTH(A12)+1,1) -> 34304 | C13: 145202 | D13: 22018 | F13: 3194.7 | K13: 2111.25
A14: =DATE(YEAR(A13),MONTH(A13)+1,1) -> 34335 | C14: 146056 | D14: 19817 | E14: 1596.725 | F14: 2666.5 | K14: 2115.25
A15: =DATE(YEAR(A14),MONTH(A14)+1,1) -> 34366 | C15: 151068 | D15: 23497 | E15: 1501.462 | F15: 2799.6 | K15: 2145.125
A16: =DATE(YEAR(A15),MONTH(A15)+1,1) -> 34394 | C16: 148829 | D16: 20979 | E16: 1119.373 | F16: 3032.3 | K16: 2155
A17: =DATE(YEAR(A16),MONTH(A16)+1,1) -> 34425 | C17: 150059 | D17: 23272 | E17: 1537.866 | F17: 3133.8 | K17: 2156.5
A18: =DATE(YEAR(A17),MONTH(A17)+1,1) -> 34455 | C18: 150909 | D18: 24443 | E18: 1740.532 | F18: 3209.8 | K18: 2164.25
A19: =DATE(YEAR(A18),MONTH(A18)+1,1) -> 34486 | C19: 152798 | D19: 26683 | E19: 1846.132 | F19: 3567.8 | K19: 2169.975
A20: =DATE(YEAR(A19),MONTH(A19)+1,1) -> 34516 | C20: 154865 | D20: 26772 | E20: 1941.721 | F20: 3514.9 | K20: 2165.375
A21: =DATE(YEAR(A20),MONTH(A20)+1,1) -> 34547 | C21: 158963 | D21: 29152 | E21: 1990.422 | F21: 3592.2 | K21: 2173.75
A22: =DATE(YEAR(A21),MONTH(A21)+1,1) -> 34578 | C22: 162900 | D22: 30798 | E22: 2003.659 | F22: 3481.2 | K22: 2176.05
A23: =DATE(YEAR(A22),MONTH(A22)+1,1) -> 34608 | C23: 165407 | D23: 32409 | E23: 2103.594 | F23: 3646.3 | K23: 2171.125
A24: =DATE(YEAR(A23),MONTH(A23)+1,1) -> 34639 | C24: 168542 | D24: 33172 | E24: 2014.794 | F24: 3640.9 | K24: 2178.55
A25: =DATE(YEAR(A24),MONTH(A24)+1,1) -> 34669 | C25: 174512 | D25: 30766 | E25: 2082.242 | F25: 3768.1 | K25: 2198
... A49: =DATE(YEAR(A48),MONTH(A48)+1,1) -> 35400 | C49: 288632 | D49: 30736 | E49: 2279.318 | F49: 4682.4838 | K49: 2362.5
A50: =DATE(YEAR(A49),MONTH(A49)+1,1) -> 35431 | C50: 290853 | D50: 31760 | E50: 2182.03 | F50: 4243.0189 | J50: 4.7991071 | K50: 2376.5
A51: =DATE(YEAR(A50),MONTH(A50)+1,1) -> 35462 | C51: 293240 | D51: 24233 | E51: 1248.746 | F51: 4078.0486 | J51: 4.2159023 | K51: 2406
A52: =DATE(YEAR(A51),MONTH(A51)+1,1) -> 35490 | C52: 294581 | D52: 33439 | E52: 2158.355 | F52: 4083.6872 | J52: 4.8387097 | K52: 2418
A53: =DATE(YEAR(A52),MONTH(A52)+1,1) -> 35521 | C53: 299277 | D53: 34974 | E53: 2258.052 | F53: 4180.8499 | J53: 4.9552719 | K53: 2433
A54: =DATE(YEAR(A53),MONTH(A53)+1,1) -> 35551 | C54: 303667 | D54: 36996 | E54: 2179.615 | F54: 4557.8373 | J54: 4.4941576 | K54: 2440
A55: =DATE(YEAR(A54),MONTH(A54)+1,1) -> 35582 | C55: 312839 | D55: 38783 | E55: 2387.339 | F55: 4366.5901 | J55: 5.1921916 | K55: 2450
A56: =DATE(YEAR(A55),MONTH(A55)+1,1) -> 35612 | C56: 317533 | D56: 40866 | E56: 2490.787 | F56: 4585.1485 | J56: 5.2957634 | K56: 2599
A57: =DATE(YEAR(A56),MONTH(A56)+1,1) -> 35643 | C57: 325911 | D57: 42929 | E57: 2680.481 | F57: 4699.7693 | J57: 6.287485 | K57: 3035
A58: =DATE(YEAR(A57),MONTH(A57)+1,1) -> 35674 | C58: 329074 | D58: 34884 | E58: 2595.128 | F58: 4707.4073 | J58: 7.2540411 | K58: 3275
A59: =DATE(YEAR(A58),MONTH(A58)+1,1) -> 35704 | C59: 340744 | D59: 30449 | E59: 2652.263 | F59: 4557.8637 | J59: 7.8406042 | K59: 3670
A60: =DATE(YEAR(A59),MONTH(A59)+1,1) -> 35735 | C60: 330559 | D60: 18551 | E60: 2292.176 | F60: 4679.0348 | J60: 8.7498763 | K60: 3648
A61: =DATE(YEAR(A60),MONTH(A60)+1,1) -> 35765 | C61: 355643 | D61: 18845 | E61: 2276.645 | F61: 4704.3468 | J61: 10.268297 | K61: 4650
... A109: =DATE(YEAR(A108),MONTH(A108)+1,1) -> 37226 | C109: 844054 | D109: 15926 | E109: 1739.713 | F109: 4217.2256 | J109: 12.549126 | K109: 10400
A110: =DATE(YEAR(A109),MONTH(A109)+1,1) -> 37257 | C110: 838025 | D110: 22696 | E110: 2271.366 | F110: 4087.6035 | G110: 188.6 | H110: 268.8 | I110: 1630.6 | J110: 14.416929 | K110: 10320
A111: =DATE(YEAR(A110),MONTH(A110)+1,1) -> 37288 | C111: 837160 | D111: 22686 | E111: 1756.813 | F111: 4197.0381 | G111: 185.5 | H111: 285.3 | I111: 1711.4 | J111: 14.78331 | K111: 10189
A112: =DATE(YEAR(A111),MONTH(A111)+1,1) -> 37316 | C112: 831410 | D112: 28671 | E112: 1968.88 | F112: 4554.9473 | G112: 190.4 | H112: 367.8 | I112: 1804.5 | J112: 14.092395 | K112: 9655
A113: =DATE(YEAR(A112),MONTH(A112)+1,1) -> 37347 | C113: 828278 | D113: 29359 | E113: 2131.73 | F113: 4801.3074 | G113: 199.6 | H113: 383 | I113: 1800.3 | J113: 13.332456 | K113: 9316
A114: =DATE(YEAR(A113),MONTH(A113)+1,1) -> 37377 | C114: 833084 | D114: 28371 | E114: 2277.905 | F114: 4725.1402 | G114: 185 | H114: 328.7 | I114: 1984.5 | J114: 12.959326 | K114: 8785
A115: =DATE(YEAR(A114),MONTH(A114)+1,1) -> 37408 | C115: 838635 | D115: 27127 | E115: 2159.607 | F115: 5094.9307 | G115: 213.8 | H115: 313.4 | I115: 1911.7 | J115: 11.443007 | K115: 8730
A116: =DATE(YEAR(A115),MONTH(A115)+1,1) -> 37438 | C116: 852717 | D116: 26905 | E116: 2430.137 | F116: 5001.7741 | G116: 231.4 | H116: 338.2 | I116: 2076.6 | J116: 9.8941558 | K116: 9108
A117: =DATE(YEAR(A116),MONTH(A116)+1,1) -> 37469 | C117: 856834 | D117: 27222 | E117: 2624.068 | F117: 4927.5434 | G117: 239.3 | H117: 388.2 | I117: 2196.3 | J117: 10.521713 | K117: 8867
A118: =DATE(YEAR(A117),MONTH(A117)+1,1) -> 37500 | C118: 859706 | D118: 27421 | E118: 2644.31 | F118: 5142.2919 | G118: 215.9 | H118: 533.5 | I118: 2110.7 | J118: 10.433135 | K118: 9015
A119: =DATE(YEAR(A118),MONTH(A118)+1,1) -> 37530 | C119: 863009 | D119: 30976 | E119: 2807.327 | F119: 5328.4017 | G119: 250.7 | H119: 395.1 | I119: 2459 | J119: 10.212913 | K119: 9233
A120: =DATE(YEAR(A119),MONTH(A119)+1,1) -> 37561 | C120: 870047 | D120: 28378 | E120: 2449.652 | F120: 4437.1948 | G120: 281.7 | H120: 458.7 | I120: 2215.5 | J120: 10.349367 | K120: 8976
A121: =DATE(YEAR(A120),MONTH(A120)+1,1) -> 37591 | C121: 883908 | D121: 17982 | E121: 1669.786 | F121: 4860.5984 | G121: 268.5 | H121: 808.9 | I121: 2326.4 | J121: 9.8745236 | K121: 8940
... A136: =DATE(YEAR(A135),MONTH(A135)+1,1) -> 38047 | C136: 927302 | D136: 39288 | E136: 2270.065 | F136: 5086.8794 | G136: 300.68 | H136: 381.28 | I136: 2787.76 | J136: 5.111912 | K136: 8587
A137: =DATE(YEAR(A136),MONTH(A136)+1,1) -> 38078 | B137: 56.7 | C137: 928584 | D137: 39813 | E137: 2218.095 | F137: 5275.3755 | G137: 290.13 | H137: 454.76 | I137: 2804.95 | J137: 5.9151997 | K137: 8661
A138: =DATE(YEAR(A137),MONTH(A137)+1,1) -> 38108 | B138: 56.4 | C138: 951848 | D138: 39924 | E138: 2373.271 | F138: 5590.6982 | G138: 288.23 | H138: 419.85 | I138: 2721.02 | J138: 6.4692569 | K138: 9210
A139: =DATE(YEAR(A138),MONTH(A138)+1,1) -> 38139 | B139: 53.4 | C139: 973397 | D139: 42769 | E139: 2590.119 | F139: 5930.964 | G139: 319.96 | H139: 564.95 | I139: 2897.01 | J139: 6.8273849 | K139: 9415
A140: =DATE(YEAR(A139),MONTH(A139)+1,1) -> 38169 | B140: 53.1 | C140: 974096 | D140: 38481 | E140: 2647.881 | F140: 5968.154 | G140: 300.5 | H140: 657.2 | I140: 3233 | J140: 7.2013555 | K140: 9168
A141: =DATE(YEAR(A140),MONTH(A140)+1,1) -> 38200 | B141: 52.3 | C141: 982669 | D141: 38680 | E141: 2875.55 | F141: 6391.029 | G141: 347.77 | H141: 605.23 | I141: 3147.84 | J141: 6.6729059 | K141: 9328
A142: =DATE(YEAR(A141),MONTH(A141)+1,1) -> 38231 | B142: 52.5 | C142: 988174 | D142: 45355 | E142: 2921.749 | F142: 7240.0304 | G142: 343.96 | H142: 600.6 | I142: 3300.91 | J142: 6.2738883 | K142: 9170
A143: =DATE(YEAR(A142),MONTH(A142)+1,1) -> 38261 | B143: 51.5 | C143: 998166 | D143: 50815 | E143: 2966.786 | F143: 7404.5939 | G143: 337.58 | H143: 626.5 | I143: 3192.42 | J143: 6.2169925 | K143: 9090
A144: =DATE(YEAR(A143),MONTH(A143)+1,1) -> 38292 | B144: 51.5 | C144: 1001587 | D144: 35157 | E144: 1998.412 | F144: 6119.8183 | G144: 298 | H144: 569.91 | I144: 3027.38 | J144: 6.1782796 | K144: 9018
A145: =DATE(YEAR(A144),MONTH(A144)+1,1) -> 38322 | B145: 50.8 | C145: 1033877 | D145: 48674 | E145: 2800.148 | F145: 6626.3036 | G145: 381.98 | H145: 789.87 | I145: 3800.98 | J145: 6.4008012 | K145: 9290
A146: =DATE(YEAR(A145),MONTH(A145)+1,1) -> 38353 | B146: 52.2 | C146: 1017491 | D146: 45480 | E146: 2244.897 | F146: 6132.2813 | G146: 335.86 | H146: 602.64 | I146: 3182.9 | J146: 7.3155274 | K146: 9165
A147: =DATE(YEAR(A146),MONTH(A146)+1,1) -> 38384 | B147: 53 | C147: 1014376 | D147: 45718 | E147: 2318.325 | F147: 6381.5818 | G147: 325.34 | H147: 668.15 | I147: 3288.14 | J147: 7.1538531 | K147: 9260
A148: =DATE(YEAR(A147),MONTH(A147)+1,1) -> 38412 | B148: 54.2 | C148: 1022703 | D148: 52765 | E148: 2645.113 | F148: 7364.7226 | G148: 380.92 | H148: 592.85 | I148: 4203.35 | J148: 8.8062799 | K148: 9480
... A151: =DATE(YEAR(A150),MONTH(A150)+1,1) -> 38504 | B151: 52.5 | C151: 1076526 | D151: 49358 | E151: 2762.983 | F151: 6894.0983 | G151: 358.24 | H151: 707.11 | I151: 3755.31 | J151: 7.422426 | K151: 9713
A152: =DATE(YEAR(A151),MONTH(A151)+1,1) -> 38534 | B152: 52.6 | C152: 1092206 | D152: 49387 | E152: 2792.71 | F152: 7153.9193 | G152: 350.43 | H152: 751.68 | I152: 3883.4 | J152: 7.8415876 | K152: 9819 | L152: 8.5
A153: =DATE(YEAR(A152),MONTH(A152)+1,1) -> 38565 | B153: 52.3 | C153: 1119102 | D153: 50608 | E153: 3095.209 | F153: 7274.8253 | G153: 438.9 | H153: 808.49 | I153: 4240.19 | J153: 8.3347956 | K153: 10240 | L153: 8.75
A154: =DATE(YEAR(A153),MONTH(A153)+1,1) -> 38596 | B154: 53.5 | C154: 1154053 | D154: 44044 | E154: 3044.675 | F154: 7521.9723 | G154: 463.93 | H154: 664.53 | I154: 3792.27 | J154: 9.0614035 | K154: 10310 | L154: 10
A155: =DATE(YEAR(A154),MONTH(A154)+1,1) -> 38626 | B155: 52.3 | C155: 1168842 | D155: 35103 | E155: 2784.785 | F155: 7951.459 | G155: 440.68 | H155: 616.73 | I155: 3806.08 | J155: 17.890789 | K155: 10090 | L155: 11
A156: =DATE(YEAR(A155),MONTH(A155)+1,1) -> 38657 | B156: 52.3 | C156: 1169085 | D156: 26119 | E156: 2062.734 | F156: 6885.5321 | G156: 331.8 | H156: 596.23 | I156: 3162.68 | J156: 18.381463 | K156: 10035 | L156: 12.25
A157: =DATE(YEAR(A156),MONTH(A156)+1,1) -> 38687 | B157: 53.2 | C157: 1202762 | D157: 32870 | E157: 2644.343 | F157: 8123.6015 | G157: 432.39 | H157: 804.48 | I157: 3652.64 | J157: 17.114496 | K157: 9830 | L157: 12.75
A158: =DATE(YEAR(A157),MONTH(A157)+1,1) -> 38718 | B158: 52 | C158: 1194939 | D158: 26622 | E158: 2243.182 | F158: 7558.5937 | G158: 371.12 | H158: 789.96 | I158: 3227.9 | J158: 17.033662 | K158: 9395 | L158: 12.75
A159: =DATE(YEAR(A158),MONTH(A158)+1,1) -> 38749 | B159: 53.2 | C159: 1197772 | D159: 25957 | E159: 2219.312 | F159: 7397.5387 | G159: 381.81 | H159: 645.86 | I159: 3500.25 | J159: 17.915998 | K159: 9230 | L159: 12.75
A160: =DATE(YEAR(A159),MONTH(A159)+1,1) -> 38777 | B160: 51.9 | C160: 1198748 | D160: 26833 | E160: 2505.406 | F160: 7495.914 | G160: 377.61 | H160: 607.85 | I160: 3424.65 | J160: 15.739282 | K160: 9075 | L160: 12.75
A161: =DATE(YEAR(A160),MONTH(A160)+1,1) -> 38808 | B161: 54.2 | C161: 1197122 | D161: 22577 | E161: 2364.224 | F161: 7641.3089 | G161: 380.23 | H161: 791.81 | I161: 3607.63 | J161: 15.404959 | K161: 8775 | L161: 12.75
A162: =DATE(YEAR(A161),MONTH(A161)+1,1) -> 38838 | B162: 53.5 | C162: 1241865 | D162: 23079 | E162: 2587.371 | F162: 8369.6635 | G162: 340.21 | H162: 760.79 | I162: 3996.22 | J162: 15.595876 | K162: 9220 | L162: 12.5
A163: =DATE(YEAR(A162),MONTH(A162)+1,1) -> 38869 | B163: 53.6 | C163: 1257785 | D163: 24566 | E163: 2631.874 | F163: 8454.1306 | G163: 396.01 | H163: 768.68 | I163: 4560.21 | J163: 15.53422 | K163: 9300 | L163: 12.5
... A399: =DATE(YEAR(A398),MONTH(A398)+1,1) -> 46054 | B399: 52 | C399: 10089900 | D399: 81250 | E399: 4950 | F399: 22166.8 | G399: 1758 | H399: 4611.7 | I399: 14523.8 | J399: 4.76 | K399: 16779 | L399: 4.75
A400: =DATE(YEAR(A399),MONTH(A399)+1,1) -> 46082 | B400: 50.7 | C400: 10355100 | D400: 61271 | F400: 22526.8 | G400: 1553.5 | H400: 3885.4 | I400: 13766.9 | J400: 3.48 | K400: 16999 | L400: 4.75
A401: =DATE(YEAR(A400),MONTH(A400)+1,1) -> 46113 | K401: 13378 | L401: 4.75
A402: =DATE(YEAR(A401),MONTH(A401)+1,1) -> 46143
A403: =DATE(YEAR(A402),MONTH(A402)+1,1) -> 46174
A404: =DATE(YEAR(A403),MONTH(A403)+1,1) -> 46204
A405: =DATE(YEAR(A404),MONTH(A404)+1,1) -> 46235
A406: =DATE(YEAR(A405),MONTH(A405)+1,1) -> 46266
A407: =DATE(YEAR(A406),MONTH(A406)+1,1) -> 46296
A408: =DATE(YEAR(A407),MONTH(A407)+1,1) -> 46327
A409: =DATE(YEAR(A408),MONTH(A408)+1,1) -> 46357

Sheet Calendar
A1: Economic Indicators | B1: INCLUDE | C1: =DATE(Settings!$B$2,1,1) -> 33970 | D1: =IF(YEAR(DATE(YEAR(C1),MONTH(C1)+1,1))<=Settings!$B$3,DATE(YEAR(C1),MONTH(C1)+1,1),0) -> 34001 | E1: =IF(YEAR(DATE(YEAR(D1),MONTH(D1)+1,1))<=Settings!$B$3,DATE(YEAR(D1),MONTH(D1)+1,1),0) -> 34029 | F1: =IF(YEAR(DATE(YEAR(E1),MONTH(E1)+1,1))<=Settings!$B$3,DATE(YEAR(E1),MONTH(E1)+1,1),0) -> 34060 | G1: =IF(YEAR(DATE(YEAR(F1),MONTH(F1)+1,1))<=Settings!$B$3,DATE(YEAR(F1),MONTH(F1)+1,1),0) -> 34090 | H1: =IF(YEAR(DATE(YEAR(G1),MONTH(G1)+1,1))<=Settings!$B$3,DATE(YEAR(G1),MONTH(G1)+1,1),0) -> 34121 | I1: =IF(YEAR(DATE(YEAR(H1),MONTH(H1)+1,1))<=Settings!$B$3,DATE(YEAR(H1),MONTH(H1)+1,1),0) -> 34151 | J1: =IF(YEAR(DATE(YEAR(I1),MONTH(I1)+1,1))<=Settings!$B$3,DATE(YEAR(I1),MONTH(I1)+1,1),0) -> 34182 | K1: =IF(YEAR(DATE(YEAR(J1),MONTH(J1)+1,1))<=Settings!$B$3,DATE(YEAR(J1),MONTH(J1)+1,1),0) -> 34213 | ... OT1: =IF(YEAR(DATE(YEAR(OS1),MONTH(OS1)+1,1))<=Settings!$B$3,DATE(YEAR(OS1),MONTH(OS1)+1,1),0) -> 46357
A2: =InfoQ!A2 -> RGDP_level | B2: =InfoQ!G2 -> 0 | E2: =IF(ISNUMBER(InfoQ!$H2),DATE(YEAR(E$1),MONTH(E$1)+InfoQ!$H2,InfoQ!$I2),0) -> 34094 | H2: =IF(ISNUMBER(InfoQ!$H2),DATE(YEAR(H$1),MONTH(H$1)+InfoQ!$H2,InfoQ!$I2),0) -> 34186 | K2: =IF(ISNUMBER(InfoQ!$H2),DATE(YEAR(K$1),MONTH(K$1)+InfoQ!$H2,InfoQ!$I2),0) -> 34278 | N2: =IF(ISNUMBER(InfoQ!$H2),DATE(YEAR(N$1),MONTH(N$1)+InfoQ!$H2,InfoQ!$I2),0) -> 34370 | Q2: =IF(ISNUMBER(InfoQ!$H2),DATE(YEAR(Q$1),MONTH(Q$1)+InfoQ!$H2,InfoQ!$I2),0) -> 34459 | T2: =IF(ISNUMBER(InfoQ!$H2),DATE(YEAR(T$1),MONTH(T$1)+InfoQ!$H2,InfoQ!$I2),0) -> 34551 | W2: =IF(ISNUMBER(InfoQ!$H2),DATE(YEAR(W$1),MONTH(W$1)+InfoQ!$H2,InfoQ!$I2),0) -> 34643 | Z2: =IF(ISNUMBER(InfoQ!$H2),DATE(YEAR(Z$1),MONTH(Z$1)+InfoQ!$H2,InfoQ!$I2),0) -> 34735 | AC2: =IF(ISNUMBER(InfoQ!$H2),DATE(YEAR(AC$1),MONTH(AC$1)+InfoQ!$H2,InfoQ!$I2),0) -> 34824 | AF2: =IF(ISNUMBER(InfoQ!$H2),DATE(YEAR(AF$1),MONTH(AF$1)+InfoQ!$H2,InfoQ!$I2),0) -> 34916 | AI2: =IF(ISNUMBER(InfoQ!$H2),DATE(YEAR(AI$1),MONTH(AI$1)+InfoQ!$H2,InfoQ!$I2),0) -> 35008 | AL2: =IF(ISNUMBER(InfoQ!$H2),DATE(YEAR(AL$1),MONTH(AL$1)+InfoQ!$H2,InfoQ!$I2),0) -> 35100 | AO2: =IF(ISNUMBER(InfoQ!$H2),DATE(YEAR(AO$1),MONTH(AO$1)+InfoQ!$H2,InfoQ!$I2),0) -> 35190 | AR2: =IF(ISNUMBER(InfoQ!$H2),DATE(YEAR(AR$1),MONTH(AR$1)+InfoQ!$H2,InfoQ!$I2),0) -> 35282 | AU2: =IF(ISNUMBER(InfoQ!$H2),DATE(YEAR(AU$1),MONTH(AU$1)+InfoQ!$H2,InfoQ!$I2),0) -> 35374 | AX2: =IF(ISNUMBER(InfoQ!$H2),DATE(YEAR(AX$1),MONTH(AX$1)+InfoQ!$H2,InfoQ!$I2),0) -> 35466 | BA2: =IF(ISNUMBER(InfoQ!$H2),DATE(YEAR(BA$1),MONTH(BA$1)+InfoQ!$H2,InfoQ!$I2),0) -> 35555 | BD2: =IF(ISNUMBER(InfoQ!$H2),DATE(YEAR(BD$1),MONTH(BD$1)+InfoQ!$H2,InfoQ!$I2),0) -> 35647 | BG2: =IF(ISNUMBER(InfoQ!$H2),DATE(YEAR(BG$1),MONTH(BG$1)+InfoQ!$H2,InfoQ!$I2),0) -> 35739 | BJ2: =IF(ISNUMBER(InfoQ!$H2),DATE(YEAR(BJ$1),MONTH(BJ$1)+InfoQ!$H2,InfoQ!$I2),0) -> 35831 | BM2: =IF(ISNUMBER(InfoQ!$H2),DATE(YEAR(BM$1),MONTH(BM$1)+InfoQ!$H2,InfoQ!$I2),0) -> 35920 | BP2: =IF(ISNUMBER(InfoQ!$H2),DATE(YEAR(BP$1),MONTH(BP$1)+InfoQ!$H2,InfoQ!$I2),0) -> 36012 | BS2: =IF(ISNUMBER(InfoQ!$H2),DATE(YEAR(BS$1),MONTH(BS$1)+InfoQ!$H2,InfoQ!$I2),0) -> 36104 | BV2: =IF(ISNUMBER(InfoQ!$H2),DATE(YEAR(BV$1),MONTH(BV$1)+InfoQ!$H2,InfoQ!$I2),0) -> 36196 | BY2: =IF(ISNUMBER(InfoQ!$H2),DATE(YEAR(BY$1),MONTH(BY$1)+InfoQ!$H2,InfoQ!$I2),0) -> 36285 | CB2: =IF(ISNUMBER(InfoQ!$H2),DATE(YEAR(CB$1),MONTH(CB$1)+InfoQ!$H2,InfoQ!$I2),0) -> 36377 | CE2: =IF(ISNUMBER(InfoQ!$H2),DATE(YEAR(CE$1),MONTH(CE$1)+InfoQ!$H2,InfoQ!$I2),0) -> 36469 | CH2: =IF(ISNUMBER(InfoQ!$H2),DATE(YEAR(CH$1),MONTH(CH$1)+InfoQ!$H2,InfoQ!$I2),0) -> 36561 | CK2: =IF(ISNUMBER(InfoQ!$H2),DATE(YEAR(CK$1),MONTH(CK$1)+InfoQ!$H2,InfoQ!$I2),0) -> 36651 | CN2: =IF(ISNUMBER(InfoQ!$H2),DATE(YEAR(CN$1),MONTH(CN$1)+InfoQ!$H2,InfoQ!$I2),0) -> 36743 | CQ2: =IF(ISNUMBER(InfoQ!$H2),DATE(YEAR(CQ$1),MONTH(CQ$1)+InfoQ!$H2,InfoQ!$I2),0) -> 36835 | CT2: =IF(ISNUMBER(InfoQ!$H2),DATE(YEAR(CT$1),MONTH(CT$1)+InfoQ!$H2,InfoQ!$I2),0) -> 36927 | CW2: =IF(ISNUMBER(InfoQ!$H2),DATE(YEAR(CW$1),MONTH(CW$1)+InfoQ!$H2,InfoQ!$I2),0) -> 37016 | CZ2: =IF(ISNUMBER(InfoQ!$H2),DATE(YEAR(CZ$1),MONTH(CZ$1)+InfoQ!$H2,InfoQ!$I2),0) -> 37108 | DC2: =IF(ISNUMBER(InfoQ!$H2),DATE(YEAR(DC$1),MONTH(DC$1)+InfoQ!$H2,InfoQ!$I2),0) -> 37200 | DF2: =IF(ISNUMBER(InfoQ!$H2),DATE(YEAR(DF$1),MONTH(DF$1)+InfoQ!$H2,InfoQ!$I2),0) -> 37292 | DI2: =IF(ISNUMBER(InfoQ!$H2),DATE(YEAR(DI$1),MONTH(DI$1)+InfoQ!$H2,InfoQ!$I2),0) -> 37381 | DL2: =IF(ISNUMBER(InfoQ!$H2),DATE(YEAR(DL$1),MONTH(DL$1)+InfoQ!$H2,InfoQ!$I2),0) -> 37473 | DO2: =IF(ISNUMBER(InfoQ!$H2),DATE(YEAR(DO$1),MONTH(DO$1)+InfoQ!$H2,InfoQ!$I2),0) -> 37565 | DR2: =IF(ISNUMBER(InfoQ!$H2),DATE(YEAR(DR$1),MONTH(DR$1)+InfoQ!$H2,InfoQ!$I2),0) -> 37657 | DU2: =IF(ISNUMBER(InfoQ!$H2),DATE(YEAR(DU$1),MONTH(DU$1)+InfoQ!$H2,InfoQ!$I2),0) -> 37746 | DX2: =IF(ISNUMBER(InfoQ!$H2),DATE(YEAR(DX$1),MONTH(DX$1)+InfoQ!$H2,InfoQ!$I2),0) -> 37838 | EA2: =IF(ISNUMBER(InfoQ!$H2),DATE(YEAR(EA$1),MONTH(EA$1)+InfoQ!$H2,InfoQ!$I2),0) -> 37930 | ED2: =IF(ISNUMBER(InfoQ!$H2),DATE(YEAR(ED$1),MONTH(ED$1)+InfoQ!$H2,InfoQ!$I2),0) -> 38022 | EG2: =IF(ISNUMBER(InfoQ!$H2),DATE(YEAR(EG$1),MONTH(EG$1)+InfoQ!$H2,InfoQ!$I2),0) -> 38112 | EJ2: =IF(ISNUMBER(InfoQ!$H2),DATE(YEAR(EJ$1),MONTH(EJ$1)+InfoQ!$H2,InfoQ!$I2),0) -> 38204 | EM2: =IF(ISNUMBER(InfoQ!$H2),DATE(YEAR(EM$1),MONTH(EM$1)+InfoQ!$H2,InfoQ!$I2),0) -> 38296 | EP2: =IF(ISNUMBER(InfoQ!$H2),DATE(YEAR(EP$1),MONTH(EP$1)+InfoQ!$H2,InfoQ!$I2),0) -> 38388 | ES2: =IF(ISNUMBER(InfoQ!$H2),DATE(YEAR(ES$1),MONTH(ES$1)+InfoQ!$H2,InfoQ!$I2),0) -> 38477 | EV2: =IF(ISNUMBER(InfoQ!$H2),DATE(YEAR(EV$1),MONTH(EV$1)+InfoQ!$H2,InfoQ!$I2),0) -> 38569 | EY2: =IF(ISNUMBER(InfoQ!$H2),DATE(YEAR(EY$1),MONTH(EY$1)+InfoQ!$H2,InfoQ!$I2),0) -> 38661 | FB2: =IF(ISNUMBER(InfoQ!$H2),DATE(YEAR(FB$1),MONTH(FB$1)+InfoQ!$H2,InfoQ!$I2),0) -> 38753 | FE2: =IF(ISNUMBER(InfoQ!$H2),DATE(YEAR(FE$1),MONTH(FE$1)+InfoQ!$H2,InfoQ!$I2),0) -> 38842 | FH2: =IF(ISNUMBER(InfoQ!$H2),DATE(YEAR(FH$1),MONTH(FH$1)+InfoQ!$H2,InfoQ!$I2),0) -> 38934 | FK2: =IF(ISNUMBER(InfoQ!$H2),DATE(YEAR(FK$1),MONTH(FK$1)+InfoQ!$H2,InfoQ!$I2),0) -> 39026 | FN2: =IF(ISNUMBER(InfoQ!$H2),DATE(YEAR(FN$1),MONTH(FN$1)+InfoQ!$H2,InfoQ!$I2),0) -> 39118 | FQ2: =IF(ISNUMBER(InfoQ!$H2),DATE(YEAR(FQ$1),MONTH(FQ$1)+InfoQ!$H2,InfoQ!$I2),0) -> 39207 | FT2: =IF(ISNUMBER(InfoQ!$H2),DATE(YEAR(FT$1),MONTH(FT$1)+InfoQ!$H2,InfoQ!$I2),0) -> 39299 | FW2: =IF(ISNUMBER(InfoQ!$H2),DATE(YEAR(FW$1),MONTH(FW$1)+InfoQ!$H2,InfoQ!$I2),0) -> 39391 | FZ2: =IF(ISNUMBER(InfoQ!$H2),DATE(YEAR(FZ$1),MONTH(FZ$1)+InfoQ!$H2,InfoQ!$I2),0) -> 39483 | GC2: =IF(ISNUMBER(InfoQ!$H2),DATE(YEAR(GC$1),MONTH(GC$1)+InfoQ!$H2,InfoQ!$I2),0) -> 39573 | GF2: =IF(ISNUMBER(InfoQ!$H2),DATE(YEAR(GF$1),MONTH(GF$1)+InfoQ!$H2,InfoQ!$I2),0) -> 39665 | GI2: =IF(ISNUMBER(InfoQ!$H2),DATE(YEAR(GI$1),MONTH(GI$1)+InfoQ!$H2,InfoQ!$I2),0) -> 39757 | GL2: =IF(ISNUMBER(InfoQ!$H2),DATE(YEAR(GL$1),MONTH(GL$1)+InfoQ!$H2,InfoQ!$I2),0) -> 39849 | GO2: =IF(ISNUMBER(InfoQ!$H2),DATE(YEAR(GO$1),MONTH(GO$1)+InfoQ!$H2,InfoQ!$I2),0) -> 39938 | GR2: =IF(ISNUMBER(InfoQ!$H2),DATE(YEAR(GR$1),MONTH(GR$1)+InfoQ!$H2,InfoQ!$I2),0) -> 40030 | GU2: =IF(ISNUMBER(InfoQ!$H2),DATE(YEAR(GU$1),MONTH(GU$1)+InfoQ!$H2,InfoQ!$I2),0) -> 40122 | GX2: =IF(ISNUMBER(InfoQ!$H2),DATE(YEAR(GX$1),MONTH(GX$1)+InfoQ!$H2,InfoQ!$I2),0) -> 40214 | HA2: =IF(ISNUMBER(InfoQ!$H2),DATE(YEAR(HA$1),MONTH(HA$1)+InfoQ!$H2,InfoQ!$I2),0) -> 40303 | HD2: =IF(ISNUMBER(InfoQ!$H2),DATE(YEAR(HD$1),MONTH(HD$1)+InfoQ!$H2,InfoQ!$I2),0) -> 40395 | HG2: =IF(ISNUMBER(InfoQ!$H2),DATE(YEAR(HG$1),MONTH(HG$1)+InfoQ!$H2,InfoQ!$I2),0) -> 40487 | HJ2: =IF(ISNUMBER(InfoQ!$H2),DATE(YEAR(HJ$1),MONTH(HJ$1)+InfoQ!$H2,InfoQ!$I2),0) -> 40579 | HM2: =IF(ISNUMBER(InfoQ!$H2),DATE(YEAR(HM$1),MONTH(HM$1)+InfoQ!$H2,InfoQ!$I2),0) -> 40668 | HP2: =IF(ISNUMBER(InfoQ!$H2),DATE(YEAR(HP$1),MONTH(HP$1)+InfoQ!$H2,InfoQ!$I2),0) -> 40760 | HS2: =IF(ISNUMBER(InfoQ!$H2),DATE(YEAR(HS$1),MONTH(HS$1)+InfoQ!$H2,InfoQ!$I2),0) -> 40852 | HV2: =IF(ISNUMBER(InfoQ!$H2),DATE(YEAR(HV$1),MONTH(HV$1)+InfoQ!$H2,InfoQ!$I2),0) -> 40944 | HY2: =IF(ISNUMBER(InfoQ!$H2),DATE(YEAR(HY$1),MONTH(HY$1)+InfoQ!$H2,InfoQ!$I2),0) -> 41034 | IB2: =IF(ISNUMBER(InfoQ!$H2),DATE(YEAR(IB$1),MONTH(IB$1)+InfoQ!$H2,InfoQ!$I2),0) -> 41126 | IE2: =IF(ISNUMBER(InfoQ!$H2),DATE(YEAR(IE$1),MONTH(IE$1)+InfoQ!$H2,InfoQ!$I2),0) -> 41218 | IH2: =IF(ISNUMBER(InfoQ!$H2),DATE(YEAR(IH$1),MONTH(IH$1)+InfoQ!$H2,InfoQ!$I2),0) -> 41310 | IK2: =IF(ISNUMBER(InfoQ!$H2),DATE(YEAR(IK$1),MONTH(IK$1)+InfoQ!$H2,InfoQ!$I2),0) -> 41399 | IN2: =IF(ISNUMBER(InfoQ!$H2),DATE(YEAR(IN$1),MONTH(IN$1)+InfoQ!$H2,InfoQ!$I2),0) -> 41491 | IQ2: =IF(ISNUMBER(InfoQ!$H2),DATE(YEAR(IQ$1),MONTH(IQ$1)+InfoQ!$H2,InfoQ!$I2),0) -> 41583 | IT2: =IF(ISNUMBER(InfoQ!$H2),DATE(YEAR(IT$1),MONTH(IT$1)+InfoQ!$H2,InfoQ!$I2),0) -> 41675 | IW2: =IF(ISNUMBER(InfoQ!$H2),DATE(YEAR(IW$1),MONTH(IW$1)+InfoQ!$H2,InfoQ!$I2),0) -> 41764 | IZ2: =IF(ISNUMBER(InfoQ!$H2),DATE(YEAR(IZ$1),MONTH(IZ$1)+InfoQ!$H2,InfoQ!$I2),0) -> 41856 | JC2: =IF(ISNUMBER(InfoQ!$H2),DATE(YEAR(JC$1),MONTH(JC$1)+InfoQ!$H2,InfoQ!$I2),0) -> 41948 | JF2: =IF(ISNUMBER(InfoQ!$H2),DATE(YEAR(JF$1),MONTH(JF$1)+InfoQ!$H2,InfoQ!$I2),0) -> 42040 | JI2: =IF(ISNUMBER(InfoQ!$H2),DATE(YEAR(JI$1),MONTH(JI$1)+InfoQ!$H2,InfoQ!$I2),0) -> 42129 | JL2: =IF(ISNUMBER(InfoQ!$H2),DATE(YEAR(JL$1),MONTH(JL$1)+InfoQ!$H2,InfoQ!$I2),0) -> 42221 | JO2: =IF(ISNUMBER(InfoQ!$H2),DATE(YEAR(JO$1),MONTH(JO$1)+InfoQ!$H2,InfoQ!$I2),0) -> 42313 | JR2: =IF(ISNUMBER(InfoQ!$H2),DATE(YEAR(JR$1),MONTH(JR$1)+InfoQ!$H2,InfoQ!$I2),0) -> 42405 | JU2: =IF(ISNUMBER(InfoQ!$H2),DATE(YEAR(JU$1),MONTH(JU$1)+InfoQ!$H2,InfoQ!$I2),0) -> 42495 | JX2: =IF(ISNUMBER(InfoQ!$H2),DATE(YEAR(JX$1),MONTH(JX$1)+InfoQ!$H2,InfoQ!$I2),0) -> 42587 | KA2: =IF(ISNUMBER(InfoQ!$H2),DATE(YEAR(KA$1),MONTH(KA$1)+InfoQ!$H2,InfoQ!$I2),0) -> 42679 | KD2: =IF(ISNUMBER(InfoQ!$H2),DATE(YEAR(KD$1),MONTH(KD$1)+InfoQ!$H2,InfoQ!$I2),0) -> 42771 | KG2: =IF(ISNUMBER(InfoQ!$H2),DATE(YEAR(KG$1),MONTH(KG$1)+InfoQ!$H2,InfoQ!$I2),0) -> 42860 | KJ2: =IF(ISNUMBER(InfoQ!$H2),DATE(YEAR(KJ$1),MONTH(KJ$1)+InfoQ!$H2,InfoQ!$I2),0) -> 42952 | KM2: =IF(ISNUMBER(InfoQ!$H2),DATE(YEAR(KM$1),MONTH(KM$1)+InfoQ!$H2,InfoQ!$I2),0) -> 43044 | KP2: =IF(ISNUMBER(InfoQ!$H2),DATE(YEAR(KP$1),MONTH(KP$1)+InfoQ!$H2,InfoQ!$I2),0) -> 43136 | KS2: =IF(ISNUMBER(InfoQ!$H2),DATE(YEAR(KS$1),MONTH(KS$1)+InfoQ!$H2,InfoQ!$I2),0) -> 43225 | KV2: =IF(ISNUMBER(InfoQ!$H2),DATE(YEAR(KV$1),MONTH(KV$1)+InfoQ!$H2,InfoQ!$I2),0) -> 43317 | KY2: =IF(ISNUMBER(InfoQ!$H2),DATE(YEAR(KY$1),MONTH(KY$1)+InfoQ!$H2,InfoQ!$I2),0) -> 43409 | LB2: =IF(ISNUMBER(InfoQ!$H2),DATE(YEAR(LB$1),MONTH(LB$1)+InfoQ!$H2,InfoQ!$I2),0) -> 43501 | LE2: =IF(ISNUMBER(InfoQ!$H2),DATE(YEAR(LE$1),MONTH(LE$1)+InfoQ!$H2,InfoQ!$I2),0) -> 43590 | LH2: =IF(ISNUMBER(InfoQ!$H2),DATE(YEAR(LH$1),MONTH(LH$1)+InfoQ!$H2,InfoQ!$I2),0) -> 43682 | LK2: =IF(ISNUMBER(InfoQ!$H2),DATE(YEAR(LK$1),MONTH(LK$1)+InfoQ!$H2,InfoQ!$I2),0) -> 43774 | LN2: =IF(ISNUMBER(InfoQ!$H2),DATE(YEAR(LN$1),MONTH(LN$1)+InfoQ!$H2,InfoQ!$I2),0) -> 43866 | LQ2: =IF(ISNUMBER(InfoQ!$H2),DATE(YEAR(LQ$1),MONTH(LQ$1)+InfoQ!$H2,InfoQ!$I2),0) -> 43956 | LT2: =IF(ISNUMBER(InfoQ!$H2),DATE(YEAR(LT$1),MONTH(LT$1)+InfoQ!$H2,InfoQ!$I2),0) -> 44048 | LW2: =IF(ISNUMBER(InfoQ!$H2),DATE(YEAR(LW$1),MONTH(LW$1)+InfoQ!$H2,InfoQ!$I2),0) -> 44140 | LZ2: =IF(ISNUMBER(InfoQ!$H2),DATE(YEAR(LZ$1),MONTH(LZ$1)+InfoQ!$H2,InfoQ!$I2),0) -> 44232 | MC2: =IF(ISNUMBER(InfoQ!$H2),DATE(YEAR(MC$1),MONTH(MC$1)+InfoQ!$H2,InfoQ!$I2),0) -> 44321 | MF2: =IF(ISNUMBER(InfoQ!$H2),DATE(YEAR(MF$1),MONTH(MF$1)+InfoQ!$H2,InfoQ!$I2),0) -> 44413 | MI2: =IF(ISNUMBER(InfoQ!$H2),DATE(YEAR(MI$1),MONTH(MI$1)+InfoQ!$H2,InfoQ!$I2),0) -> 44505 | ML2: =IF(ISNUMBER(InfoQ!$H2),DATE(YEAR(ML$1),MONTH(ML$1)+InfoQ!$H2,InfoQ!$I2),0) -> 44597 | MO2: =IF(ISNUMBER(InfoQ!$H2),DATE(YEAR(MO$1),MONTH(MO$1)+InfoQ!$H2,InfoQ!$I2),0) -> 44686 | MR2: =IF(ISNUMBER(InfoQ!$H2),DATE(YEAR(MR$1),MONTH(MR$1)+InfoQ!$H2,InfoQ!$I2),0) -> 44778 | MU2: =IF(ISNUMBER(InfoQ!$H2),DATE(YEAR(MU$1),MONTH(MU$1)+InfoQ!$H2,InfoQ!$I2),0) -> 44870 | MX2: =IF(ISNUMBER(InfoQ!$H2),DATE(YEAR(MX$1),MONTH(MX$1)+InfoQ!$H2,InfoQ!$I2),0) -> 44962 | NA2: =IF(ISNUMBER(InfoQ!$H2),DATE(YEAR(NA$1),MONTH(NA$1)+InfoQ!$H2,InfoQ!$I2),0) -> 45051 | ND2: =IF(ISNUMBER(InfoQ!$H2),DATE(YEAR(ND$1),MONTH(ND$1)+InfoQ!$H2,InfoQ!$I2),0) -> 45143 | NG2: =IF(ISNUMBER(InfoQ!$H2),DATE(YEAR(NG$1),MONTH(NG$1)+InfoQ!$H2,InfoQ!$I2),0) -> 45235 | NJ2: =IF(ISNUMBER(InfoQ!$H2),DATE(YEAR(NJ$1),MONTH(NJ$1)+InfoQ!$H2,InfoQ!$I2),0) -> 45327 | NM2: =IF(ISNUMBER(InfoQ!$H2),DATE(YEAR(NM$1),MONTH(NM$1)+InfoQ!$H2,InfoQ!$I2),0) -> 45417 | NP2: =IF(ISNUMBER(InfoQ!$H2),DATE(YEAR(NP$1),MONTH(NP$1)+InfoQ!$H2,InfoQ!$I2),0) -> 45509 | NS2: =IF(ISNUMBER(InfoQ!$H2),DATE(YEAR(NS$1),MONTH(NS$1)+InfoQ!$H2,InfoQ!$I2),0) -> 45601 | NV2: =IF(ISNUMBER(InfoQ!$H2),DATE(YEAR(NV$1),MONTH(NV$1)+InfoQ!$H2,InfoQ!$I2),0) -> 45693 | NY2: =IF(ISNUMBER(InfoQ!$H2),DATE(YEAR(NY$1),MONTH(NY$1)+InfoQ!$H2,InfoQ!$I2),0) -> 45782 | OB2: =IF(ISNUMBER(InfoQ!$H2),DATE(YEAR(OB$1),MONTH(OB$1)+InfoQ!$H2,InfoQ!$I2),0) -> 45874 | OE2: =IF(ISNUMBER(InfoQ!$H2),DATE(YEAR(OE$1),MONTH(OE$1)+InfoQ!$H2,InfoQ!$I2),0) -> 45966 | OH2: =IF(ISNUMBER(InfoQ!$H2),DATE(YEAR(OH$1),MONTH(OH$1)+InfoQ!$H2,InfoQ!$I2),0) -> 46058 | OK2: =IF(ISNUMBER(InfoQ!$H2),DATE(YEAR(OK$1),MONTH(OK$1)+InfoQ!$H2,InfoQ!$I2),0) -> 46147 | ON2: =IF(ISNUMBER(InfoQ!$H2),DATE(YEAR(ON$1),MONTH(ON$1)+InfoQ!$H2,InfoQ!$I2),0) -> 46239 | OQ2: =IF(ISNUMBER(InfoQ!$H2),DATE(YEAR(OQ$1),MONTH(OQ$1)+InfoQ!$H2,InfoQ!$I2),0) -> 46331 | OT2: =IF(ISNUMBER(InfoQ!$H2),DATE(YEAR(OT$1),MONTH(OT$1)+InfoQ!$H2,InfoQ!$I2),0) -> 46423
A3: =InfoQ!A3 -> RGDP_growth | B3: =InfoQ!G3 -> 1 | E3: =IF(ISNUMBER(InfoQ!$H3),DATE(YEAR(E$1),MONTH(E$1)+InfoQ!$H3,InfoQ!$I3),0) -> 34094 | H3: =IF(ISNUMBER(InfoQ!$H3),DATE(YEAR(H$1),MONTH(H$1)+InfoQ!$H3,InfoQ!$I3),0) -> 34186 | K3: =IF(ISNUMBER(InfoQ!$H3),DATE(YEAR(K$1),MONTH(K$1)+InfoQ!$H3,InfoQ!$I3),0) -> 34278 | N3: =IF(ISNUMBER(InfoQ!$H3),DATE(YEAR(N$1),MONTH(N$1)+InfoQ!$H3,InfoQ!$I3),0) -> 34370 | Q3: =IF(ISNUMBER(InfoQ!$H3),DATE(YEAR(Q$1),MONTH(Q$1)+InfoQ!$H3,InfoQ!$I3),0) -> 34459 | T3: =IF(ISNUMBER(InfoQ!$H3),DATE(YEAR(T$1),MONTH(T$1)+InfoQ!$H3,InfoQ!$I3),0) -> 34551 | W3: =IF(ISNUMBER(InfoQ!$H3),DATE(YEAR(W$1),MONTH(W$1)+InfoQ!$H3,InfoQ!$I3),0) -> 34643 | Z3: =IF(ISNUMBER(InfoQ!$H3),DATE(YEAR(Z$1),MONTH(Z$1)+InfoQ!$H3,InfoQ!$I3),0) -> 34735 | AC3: =IF(ISNUMBER(InfoQ!$H3),DATE(YEAR(AC$1),MONTH(AC$1)+InfoQ!$H3,InfoQ!$I3),0) -> 34824 | AF3: =IF(ISNUMBER(InfoQ!$H3),DATE(YEAR(AF$1),MONTH(AF$1)+InfoQ!$H3,InfoQ!$I3),0) -> 34916 | AI3: =IF(ISNUMBER(InfoQ!$H3),DATE(YEAR(AI$1),MONTH(AI$1)+InfoQ!$H3,InfoQ!$I3),0) -> 35008 | AL3: =IF(ISNUMBER(InfoQ!$H3),DATE(YEAR(AL$1),MONTH(AL$1)+InfoQ!$H3,InfoQ!$I3),0) -> 35100 | AO3: =IF(ISNUMBER(InfoQ!$H3),DATE(YEAR(AO$1),MONTH(AO$1)+InfoQ!$H3,InfoQ!$I3),0) -> 35190 | AR3: =IF(ISNUMBER(InfoQ!$H3),DATE(YEAR(AR$1),MONTH(AR$1)+InfoQ!$H3,InfoQ!$I3),0) -> 35282 | AU3: =IF(ISNUMBER(InfoQ!$H3),DATE(YEAR(AU$1),MONTH(AU$1)+InfoQ!$H3,InfoQ!$I3),0) -> 35374 | AX3: =IF(ISNUMBER(InfoQ!$H3),DATE(YEAR(AX$1),MONTH(AX$1)+InfoQ!$H3,InfoQ!$I3),0) -> 35466 | BA3: =IF(ISNUMBER(InfoQ!$H3),DATE(YEAR(BA$1),MONTH(BA$1)+InfoQ!$H3,InfoQ!$I3),0) -> 35555 | BD3: =IF(ISNUMBER(InfoQ!$H3),DATE(YEAR(BD$1),MONTH(BD$1)+InfoQ!$H3,InfoQ!$I3),0) -> 35647 | BG3: =IF(ISNUMBER(InfoQ!$H3),DATE(YEAR(BG$1),MONTH(BG$1)+InfoQ!$H3,InfoQ!$I3),0) -> 35739 | BJ3: =IF(ISNUMBER(InfoQ!$H3),DATE(YEAR(BJ$1),MONTH(BJ$1)+InfoQ!$H3,InfoQ!$I3),0) -> 35831 | BM3: =IF(ISNUMBER(InfoQ!$H3),DATE(YEAR(BM$1),MONTH(BM$1)+InfoQ!$H3,InfoQ!$I3),0) -> 35920 | BP3: =IF(ISNUMBER(InfoQ!$H3),DATE(YEAR(BP$1),MONTH(BP$1)+InfoQ!$H3,InfoQ!$I3),0) -> 36012 | BS3: =IF(ISNUMBER(InfoQ!$H3),DATE(YEAR(BS$1),MONTH(BS$1)+InfoQ!$H3,InfoQ!$I3),0) -> 36104 | BV3: =IF(ISNUMBER(InfoQ!$H3),DATE(YEAR(BV$1),MONTH(BV$1)+InfoQ!$H3,InfoQ!$I3),0) -> 36196 | BY3: =IF(ISNUMBER(InfoQ!$H3),DATE(YEAR(BY$1),MONTH(BY$1)+InfoQ!$H3,InfoQ!$I3),0) -> 36285 | CB3: =IF(ISNUMBER(InfoQ!$H3),DATE(YEAR(CB$1),MONTH(CB$1)+InfoQ!$H3,InfoQ!$I3),0) -> 36377 | CE3: =IF(ISNUMBER(InfoQ!$H3),DATE(YEAR(CE$1),MONTH(CE$1)+InfoQ!$H3,InfoQ!$I3),0) -> 36469 | CH3: =IF(ISNUMBER(InfoQ!$H3),DATE(YEAR(CH$1),MONTH(CH$1)+InfoQ!$H3,InfoQ!$I3),0) -> 36561 | CK3: =IF(ISNUMBER(InfoQ!$H3),DATE(YEAR(CK$1),MONTH(CK$1)+InfoQ!$H3,InfoQ!$I3),0) -> 36651 | CN3: =IF(ISNUMBER(InfoQ!$H3),DATE(YEAR(CN$1),MONTH(CN$1)+InfoQ!$H3,InfoQ!$I3),0) -> 36743 | CQ3: =IF(ISNUMBER(InfoQ!$H3),DATE(YEAR(CQ$1),MONTH(CQ$1)+InfoQ!$H3,InfoQ!$I3),0) -> 36835 | CT3: =IF(ISNUMBER(InfoQ!$H3),DATE(YEAR(CT$1),MONTH(CT$1)+InfoQ!$H3,InfoQ!$I3),0) -> 36927 | CW3: =IF(ISNUMBER(InfoQ!$H3),DATE(YEAR(CW$1),MONTH(CW$1)+InfoQ!$H3,InfoQ!$I3),0) -> 37016 | CZ3: =IF(ISNUMBER(InfoQ!$H3),DATE(YEAR(CZ$1),MONTH(CZ$1)+InfoQ!$H3,InfoQ!$I3),0) -> 37108 | DC3: =IF(ISNUMBER(InfoQ!$H3),DATE(YEAR(DC$1),MONTH(DC$1)+InfoQ!$H3,InfoQ!$I3),0) -> 37200 | DF3: =IF(ISNUMBER(InfoQ!$H3),DATE(YEAR(DF$1),MONTH(DF$1)+InfoQ!$H3,InfoQ!$I3),0) -> 37292 | DI3: =IF(ISNUMBER(InfoQ!$H3),DATE(YEAR(DI$1),MONTH(DI$1)+InfoQ!$H3,InfoQ!$I3),0) -> 37381 | DL3: =IF(ISNUMBER(InfoQ!$H3),DATE(YEAR(DL$1),MONTH(DL$1)+InfoQ!$H3,InfoQ!$I3),0) -> 37473 | DO3: =IF(ISNUMBER(InfoQ!$H3),DATE(YEAR(DO$1),MONTH(DO$1)+InfoQ!$H3,InfoQ!$I3),0) -> 37565 | DR3: =IF(ISNUMBER(InfoQ!$H3),DATE(YEAR(DR$1),MONTH(DR$1)+InfoQ!$H3,InfoQ!$I3),0) -> 37657 | DU3: =IF(ISNUMBER(InfoQ!$H3),DATE(YEAR(DU$1),MONTH(DU$1)+InfoQ!$H3,InfoQ!$I3),0) -> 37746 | DX3: =IF(ISNUMBER(InfoQ!$H3),DATE(YEAR(DX$1),MONTH(DX$1)+InfoQ!$H3,InfoQ!$I3),0) -> 37838 | EA3: =IF(ISNUMBER(InfoQ!$H3),DATE(YEAR(EA$1),MONTH(EA$1)+InfoQ!$H3,InfoQ!$I3),0) -> 37930 | ED3: =IF(ISNUMBER(InfoQ!$H3),DATE(YEAR(ED$1),MONTH(ED$1)+InfoQ!$H3,InfoQ!$I3),0) -> 38022 | EG3: =IF(ISNUMBER(InfoQ!$H3),DATE(YEAR(EG$1),MONTH(EG$1)+InfoQ!$H3,InfoQ!$I3),0) -> 38112 | EJ3: =IF(ISNUMBER(InfoQ!$H3),DATE(YEAR(EJ$1),MONTH(EJ$1)+InfoQ!$H3,InfoQ!$I3),0) -> 38204 | EM3: =IF(ISNUMBER(InfoQ!$H3),DATE(YEAR(EM$1),MONTH(EM$1)+InfoQ!$H3,InfoQ!$I3),0) -> 38296 | EP3: =IF(ISNUMBER(InfoQ!$H3),DATE(YEAR(EP$1),MONTH(EP$1)+InfoQ!$H3,InfoQ!$I3),0) -> 38388 | ES3: =IF(ISNUMBER(InfoQ!$H3),DATE(YEAR(ES$1),MONTH(ES$1)+InfoQ!$H3,InfoQ!$I3),0) -> 38477 | EV3: =IF(ISNUMBER(InfoQ!$H3),DATE(YEAR(EV$1),MONTH(EV$1)+InfoQ!$H3,InfoQ!$I3),0) -> 38569 | EY3: =IF(ISNUMBER(InfoQ!$H3),DATE(YEAR(EY$1),MONTH(EY$1)+InfoQ!$H3,InfoQ!$I3),0) -> 38661 | FB3: =IF(ISNUMBER(InfoQ!$H3),DATE(YEAR(FB$1),MONTH(FB$1)+InfoQ!$H3,InfoQ!$I3),0) -> 38753 | FE3: =IF(ISNUMBER(InfoQ!$H3),DATE(YEAR(FE$1),MONTH(FE$1)+InfoQ!$H3,InfoQ!$I3),0) -> 38842 | FH3: =IF(ISNUMBER(InfoQ!$H3),DATE(YEAR(FH$1),MONTH(FH$1)+InfoQ!$H3,InfoQ!$I3),0) -> 38934 | FK3: =IF(ISNUMBER(InfoQ!$H3),DATE(YEAR(FK$1),MONTH(FK$1)+InfoQ!$H3,InfoQ!$I3),0) -> 39026 | FN3: =IF(ISNUMBER(InfoQ!$H3),DATE(YEAR(FN$1),MONTH(FN$1)+InfoQ!$H3,InfoQ!$I3),0) -> 39118 | FQ3: =IF(ISNUMBER(InfoQ!$H3),DATE(YEAR(FQ$1),MONTH(FQ$1)+InfoQ!$H3,InfoQ!$I3),0) -> 39207 | FT3: =IF(ISNUMBER(InfoQ!$H3),DATE(YEAR(FT$1),MONTH(FT$1)+InfoQ!$H3,InfoQ!$I3),0) -> 39299 | FW3: =IF(ISNUMBER(InfoQ!$H3),DATE(YEAR(FW$1),MONTH(FW$1)+InfoQ!$H3,InfoQ!$I3),0) -> 39391 | FZ3: =IF(ISNUMBER(InfoQ!$H3),DATE(YEAR(FZ$1),MONTH(FZ$1)+InfoQ!$H3,InfoQ!$I3),0) -> 39483 | GC3: =IF(ISNUMBER(InfoQ!$H3),DATE(YEAR(GC$1),MONTH(GC$1)+InfoQ!$H3,InfoQ!$I3),0) -> 39573 | GF3: =IF(ISNUMBER(InfoQ!$H3),DATE(YEAR(GF$1),MONTH(GF$1)+InfoQ!$H3,InfoQ!$I3),0) -> 39665 | GI3: =IF(ISNUMBER(InfoQ!$H3),DATE(YEAR(GI$1),MONTH(GI$1)+InfoQ!$H3,InfoQ!$I3),0) -> 39757 | GL3: =IF(ISNUMBER(InfoQ!$H3),DATE(YEAR(GL$1),MONTH(GL$1)+InfoQ!$H3,InfoQ!$I3),0) -> 39849 | GO3: =IF(ISNUMBER(InfoQ!$H3),DATE(YEAR(GO$1),MONTH(GO$1)+InfoQ!$H3,InfoQ!$I3),0) -> 39938 | GR3: =IF(ISNUMBER(InfoQ!$H3),DATE(YEAR(GR$1),MONTH(GR$1)+InfoQ!$H3,InfoQ!$I3),0) -> 40030 | GU3: =IF(ISNUMBER(InfoQ!$H3),DATE(YEAR(GU$1),MONTH(GU$1)+InfoQ!$H3,InfoQ!$I3),0) -> 40122 | GX3: =IF(ISNUMBER(InfoQ!$H3),DATE(YEAR(GX$1),MONTH(GX$1)+InfoQ!$H3,InfoQ!$I3),0) -> 40214 | HA3: =IF(ISNUMBER(InfoQ!$H3),DATE(YEAR(HA$1),MONTH(HA$1)+InfoQ!$H3,InfoQ!$I3),0) -> 40303 | HD3: =IF(ISNUMBER(InfoQ!$H3),DATE(YEAR(HD$1),MONTH(HD$1)+InfoQ!$H3,InfoQ!$I3),0) -> 40395 | HG3: =IF(ISNUMBER(InfoQ!$H3),DATE(YEAR(HG$1),MONTH(HG$1)+InfoQ!$H3,InfoQ!$I3),0) -> 40487 | HJ3: =IF(ISNUMBER(InfoQ!$H3),DATE(YEAR(HJ$1),MONTH(HJ$1)+InfoQ!$H3,InfoQ!$I3),0) -> 40579 | HM3: =IF(ISNUMBER(InfoQ!$H3),DATE(YEAR(HM$1),MONTH(HM$1)+InfoQ!$H3,InfoQ!$I3),0) -> 40668 | HP3: =IF(ISNUMBER(InfoQ!$H3),DATE(YEAR(HP$1),MONTH(HP$1)+InfoQ!$H3,InfoQ!$I3),0) -> 40760 | HS3: =IF(ISNUMBER(InfoQ!$H3),DATE(YEAR(HS$1),MONTH(HS$1)+InfoQ!$H3,InfoQ!$I3),0) -> 40852 | HV3: =IF(ISNUMBER(InfoQ!$H3),DATE(YEAR(HV$1),MONTH(HV$1)+InfoQ!$H3,InfoQ!$I3),0) -> 40944 | HY3: =IF(ISNUMBER(InfoQ!$H3),DATE(YEAR(HY$1),MONTH(HY$1)+InfoQ!$H3,InfoQ!$I3),0) -> 41034 | IB3: =IF(ISNUMBER(InfoQ!$H3),DATE(YEAR(IB$1),MONTH(IB$1)+InfoQ!$H3,InfoQ!$I3),0) -> 41126 | IE3: =IF(ISNUMBER(InfoQ!$H3),DATE(YEAR(IE$1),MONTH(IE$1)+InfoQ!$H3,InfoQ!$I3),0) -> 41218 | IH3: =IF(ISNUMBER(InfoQ!$H3),DATE(YEAR(IH$1),MONTH(IH$1)+InfoQ!$H3,InfoQ!$I3),0) -> 41310 | IK3: =IF(ISNUMBER(InfoQ!$H3),DATE(YEAR(IK$1),MONTH(IK$1)+InfoQ!$H3,InfoQ!$I3),0) -> 41399 | IN3: =IF(ISNUMBER(InfoQ!$H3),DATE(YEAR(IN$1),MONTH(IN$1)+InfoQ!$H3,InfoQ!$I3),0) -> 41491 | IQ3: =IF(ISNUMBER(InfoQ!$H3),DATE(YEAR(IQ$1),MONTH(IQ$1)+InfoQ!$H3,InfoQ!$I3),0) -> 41583 | IT3: =IF(ISNUMBER(InfoQ!$H3),DATE(YEAR(IT$1),MONTH(IT$1)+InfoQ!$H3,InfoQ!$I3),0) -> 41675 | IW3: =IF(ISNUMBER(InfoQ!$H3),DATE(YEAR(IW$1),MONTH(IW$1)+InfoQ!$H3,InfoQ!$I3),0) -> 41764 | IZ3: =IF(ISNUMBER(InfoQ!$H3),DATE(YEAR(IZ$1),MONTH(IZ$1)+InfoQ!$H3,InfoQ!$I3),0) -> 41856 | JC3: =IF(ISNUMBER(InfoQ!$H3),DATE(YEAR(JC$1),MONTH(JC$1)+InfoQ!$H3,InfoQ!$I3),0) -> 41948 | JF3: =IF(ISNUMBER(InfoQ!$H3),DATE(YEAR(JF$1),MONTH(JF$1)+InfoQ!$H3,InfoQ!$I3),0) -> 42040 | JI3: =IF(ISNUMBER(InfoQ!$H3),DATE(YEAR(JI$1),MONTH(JI$1)+InfoQ!$H3,InfoQ!$I3),0) -> 42129 | JL3: =IF(ISNUMBER(InfoQ!$H3),DATE(YEAR(JL$1),MONTH(JL$1)+InfoQ!$H3,InfoQ!$I3),0) -> 42221 | JO3: =IF(ISNUMBER(InfoQ!$H3),DATE(YEAR(JO$1),MONTH(JO$1)+InfoQ!$H3,InfoQ!$I3),0) -> 42313 | JR3: =IF(ISNUMBER(InfoQ!$H3),DATE(YEAR(JR$1),MONTH(JR$1)+InfoQ!$H3,InfoQ!$I3),0) -> 42405 | JU3: =IF(ISNUMBER(InfoQ!$H3),DATE(YEAR(JU$1),MONTH(JU$1)+InfoQ!$H3,InfoQ!$I3),0) -> 42495 | JX3: =IF(ISNUMBER(InfoQ!$H3),DATE(YEAR(JX$1),MONTH(JX$1)+InfoQ!$H3,InfoQ!$I3),0) -> 42587 | KA3: =IF(ISNUMBER(InfoQ!$H3),DATE(YEAR(KA$1),MONTH(KA$1)+InfoQ!$H3,InfoQ!$I3),0) -> 42679 | KD3: =IF(ISNUMBER(InfoQ!$H3),DATE(YEAR(KD$1),MONTH(KD$1)+InfoQ!$H3,InfoQ!$I3),0) -> 42771 | KG3: =IF(ISNUMBER(InfoQ!$H3),DATE(YEAR(KG$1),MONTH(KG$1)+InfoQ!$H3,InfoQ!$I3),0) -> 42860 | KJ3: =IF(ISNUMBER(InfoQ!$H3),DATE(YEAR(KJ$1),MONTH(KJ$1)+InfoQ!$H3,InfoQ!$I3),0) -> 42952 | KM3: =IF(ISNUMBER(InfoQ!$H3),DATE(YEAR(KM$1),MONTH(KM$1)+InfoQ!$H3,InfoQ!$I3),0) -> 43044 | KP3: =IF(ISNUMBER(InfoQ!$H3),DATE(YEAR(KP$1),MONTH(KP$1)+InfoQ!$H3,InfoQ!$I3),0) -> 43136 | KS3: =IF(ISNUMBER(InfoQ!$H3),DATE(YEAR(KS$1),MONTH(KS$1)+InfoQ!$H3,InfoQ!$I3),0) -> 43225 | KV3: =IF(ISNUMBER(InfoQ!$H3),DATE(YEAR(KV$1),MONTH(KV$1)+InfoQ!$H3,InfoQ!$I3),0) -> 43317 | KY3: =IF(ISNUMBER(InfoQ!$H3),DATE(YEAR(KY$1),MONTH(KY$1)+InfoQ!$H3,InfoQ!$I3),0) -> 43409 | LB3: =IF(ISNUMBER(InfoQ!$H3),DATE(YEAR(LB$1),MONTH(LB$1)+InfoQ!$H3,InfoQ!$I3),0) -> 43501 | LE3: =IF(ISNUMBER(InfoQ!$H3),DATE(YEAR(LE$1),MONTH(LE$1)+InfoQ!$H3,InfoQ!$I3),0) -> 43590 | LH3: =IF(ISNUMBER(InfoQ!$H3),DATE(YEAR(LH$1),MONTH(LH$1)+InfoQ!$H3,InfoQ!$I3),0) -> 43682 | LK3: =IF(ISNUMBER(InfoQ!$H3),DATE(YEAR(LK$1),MONTH(LK$1)+InfoQ!$H3,InfoQ!$I3),0) -> 43774 | LN3: =IF(ISNUMBER(InfoQ!$H3),DATE(YEAR(LN$1),MONTH(LN$1)+InfoQ!$H3,InfoQ!$I3),0) -> 43866 | LQ3: =IF(ISNUMBER(InfoQ!$H3),DATE(YEAR(LQ$1),MONTH(LQ$1)+InfoQ!$H3,InfoQ!$I3),0) -> 43956 | LT3: =IF(ISNUMBER(InfoQ!$H3),DATE(YEAR(LT$1),MONTH(LT$1)+InfoQ!$H3,InfoQ!$I3),0) -> 44048 | LW3: =IF(ISNUMBER(InfoQ!$H3),DATE(YEAR(LW$1),MONTH(LW$1)+InfoQ!$H3,InfoQ!$I3),0) -> 44140 | LZ3: =IF(ISNUMBER(InfoQ!$H3),DATE(YEAR(LZ$1),MONTH(LZ$1)+InfoQ!$H3,InfoQ!$I3),0) -> 44232 | MC3: =IF(ISNUMBER(InfoQ!$H3),DATE(YEAR(MC$1),MONTH(MC$1)+InfoQ!$H3,InfoQ!$I3),0) -> 44321 | MF3: =IF(ISNUMBER(InfoQ!$H3),DATE(YEAR(MF$1),MONTH(MF$1)+InfoQ!$H3,InfoQ!$I3),0) -> 44413 | MI3: =IF(ISNUMBER(InfoQ!$H3),DATE(YEAR(MI$1),MONTH(MI$1)+InfoQ!$H3,InfoQ!$I3),0) -> 44505 | ML3: =IF(ISNUMBER(InfoQ!$H3),DATE(YEAR(ML$1),MONTH(ML$1)+InfoQ!$H3,InfoQ!$I3),0) -> 44597 | MO3: =IF(ISNUMBER(InfoQ!$H3),DATE(YEAR(MO$1),MONTH(MO$1)+InfoQ!$H3,InfoQ!$I3),0) -> 44686 | MR3: =IF(ISNUMBER(InfoQ!$H3),DATE(YEAR(MR$1),MONTH(MR$1)+InfoQ!$H3,InfoQ!$I3),0) -> 44778 | MU3: =IF(ISNUMBER(InfoQ!$H3),DATE(YEAR(MU$1),MONTH(MU$1)+InfoQ!$H3,InfoQ!$I3),0) -> 44870 | MX3: =IF(ISNUMBER(InfoQ!$H3),DATE(YEAR(MX$1),MONTH(MX$1)+InfoQ!$H3,InfoQ!$I3),0) -> 44962 | NA3: =IF(ISNUMBER(InfoQ!$H3),DATE(YEAR(NA$1),MONTH(NA$1)+InfoQ!$H3,InfoQ!$I3),0) -> 45051 | ND3: =IF(ISNUMBER(InfoQ!$H3),DATE(YEAR(ND$1),MONTH(ND$1)+InfoQ!$H3,InfoQ!$I3),0) -> 45143 | NG3: =IF(ISNUMBER(InfoQ!$H3),DATE(YEAR(NG$1),MONTH(NG$1)+InfoQ!$H3,InfoQ!$I3),0) -> 45235 | NJ3: =IF(ISNUMBER(InfoQ!$H3),DATE(YEAR(NJ$1),MONTH(NJ$1)+InfoQ!$H3,InfoQ!$I3),0) -> 45327 | NM3: =IF(ISNUMBER(InfoQ!$H3),DATE(YEAR(NM$1),MONTH(NM$1)+InfoQ!$H3,InfoQ!$I3),0) -> 45417 | NP3: =IF(ISNUMBER(InfoQ!$H3),DATE(YEAR(NP$1),MONTH(NP$1)+InfoQ!$H3,InfoQ!$I3),0) -> 45509 | NS3: =IF(ISNUMBER(InfoQ!$H3),DATE(YEAR(NS$1),MONTH(NS$1)+InfoQ!$H3,InfoQ!$I3),0) -> 45601 | NV3: =IF(ISNUMBER(InfoQ!$H3),DATE(YEAR(NV$1),MONTH(NV$1)+InfoQ!$H3,InfoQ!$I3),0) -> 45693 | NY3: =IF(ISNUMBER(InfoQ!$H3),DATE(YEAR(NY$1),MONTH(NY$1)+InfoQ!$H3,InfoQ!$I3),0) -> 45782 | OB3: =IF(ISNUMBER(InfoQ!$H3),DATE(YEAR(OB$1),MONTH(OB$1)+InfoQ!$H3,InfoQ!$I3),0) -> 45874 | OE3: =IF(ISNUMBER(InfoQ!$H3),DATE(YEAR(OE$1),MONTH(OE$1)+InfoQ!$H3,InfoQ!$I3),0) -> 45966 | OH3: =IF(ISNUMBER(InfoQ!$H3),DATE(YEAR(OH$1),MONTH(OH$1)+InfoQ!$H3,InfoQ!$I3),0) -> 46058 | OK3: =IF(ISNUMBER(InfoQ!$H3),DATE(YEAR(OK$1),MONTH(OK$1)+InfoQ!$H3,InfoQ!$I3),0) -> 46147 | ON3: =IF(ISNUMBER(InfoQ!$H3),DATE(YEAR(ON$1),MONTH(ON$1)+InfoQ!$H3,InfoQ!$I3),0) -> 46239 | OQ3: =IF(ISNUMBER(InfoQ!$H3),DATE(YEAR(OQ$1),MONTH(OQ$1)+InfoQ!$H3,InfoQ!$I3),0) -> 46331 | OT3: =IF(ISNUMBER(InfoQ!$H3),DATE(YEAR(OT$1),MONTH(OT$1)+InfoQ!$H3,InfoQ!$I3),0) -> 46423
A4: =InfoQ!A4 -> Bus_Act | B4: =InfoQ!G4 -> 1 | E4: =IF(ISNUMBER(InfoQ!$H4),DATE(YEAR(E$1),MONTH(E$1)+InfoQ!$H4,InfoQ!$I4),0) -> 34076 | H4: =IF(ISNUMBER(InfoQ!$H4),DATE(YEAR(H$1),MONTH(H$1)+InfoQ!$H4,InfoQ!$I4),0) -> 34167 | K4: =IF(ISNUMBER(InfoQ!$H4),DATE(YEAR(K$1),MONTH(K$1)+InfoQ!$H4,InfoQ!$I4),0) -> 34259 | N4: =IF(ISNUMBER(InfoQ!$H4),DATE(YEAR(N$1),MONTH(N$1)+InfoQ!$H4,InfoQ!$I4),0) -> 34351 | Q4: =IF(ISNUMBER(InfoQ!$H4),DATE(YEAR(Q$1),MONTH(Q$1)+InfoQ!$H4,InfoQ!$I4),0) -> 34441 | T4: =IF(ISNUMBER(InfoQ!$H4),DATE(YEAR(T$1),MONTH(T$1)+InfoQ!$H4,InfoQ!$I4),0) -> 34532 | W4: =IF(ISNUMBER(InfoQ!$H4),DATE(YEAR(W$1),MONTH(W$1)+InfoQ!$H4,InfoQ!$I4),0) -> 34624 | Z4: =IF(ISNUMBER(InfoQ!$H4),DATE(YEAR(Z$1),MONTH(Z$1)+InfoQ!$H4,InfoQ!$I4),0) -> 34716 | AC4: =IF(ISNUMBER(InfoQ!$H4),DATE(YEAR(AC$1),MONTH(AC$1)+InfoQ!$H4,InfoQ!$I4),0) -> 34806 | AF4: =IF(ISNUMBER(InfoQ!$H4),DATE(YEAR(AF$1),MONTH(AF$1)+InfoQ!$H4,InfoQ!$I4),0) -> 34897 | AI4: =IF(ISNUMBER(InfoQ!$H4),DATE(YEAR(AI$1),MONTH(AI$1)+InfoQ!$H4,InfoQ!$I4),0) -> 34989 | AL4: =IF(ISNUMBER(InfoQ!$H4),DATE(YEAR(AL$1),MONTH(AL$1)+InfoQ!$H4,InfoQ!$I4),0) -> 35081 | AO4: =IF(ISNUMBER(InfoQ!$H4),DATE(YEAR(AO$1),MONTH(AO$1)+InfoQ!$H4,InfoQ!$I4),0) -> 35172 | AR4: =IF(ISNUMBER(InfoQ!$H4),DATE(YEAR(AR$1),MONTH(AR$1)+InfoQ!$H4,InfoQ!$I4),0) -> 35263 | AU4: =IF(ISNUMBER(InfoQ!$H4),DATE(YEAR(AU$1),MONTH(AU$1)+InfoQ!$H4,InfoQ!$I4),0) -> 35355 | AX4: =IF(ISNUMBER(InfoQ!$H4),DATE(YEAR(AX$1),MONTH(AX$1)+InfoQ!$H4,InfoQ!$I4),0) -> 35447 | BA4: =IF(ISNUMBER(InfoQ!$H4),DATE(YEAR(BA$1),MONTH(BA$1)+InfoQ!$H4,InfoQ!$I4),0) -> 35537 | BD4: =IF(ISNUMBER(InfoQ!$H4),DATE(YEAR(BD$1),MONTH(BD$1)+InfoQ!$H4,InfoQ!$I4),0) -> 35628 | BG4: =IF(ISNUMBER(InfoQ!$H4),DATE(YEAR(BG$1),MONTH(BG$1)+InfoQ!$H4,InfoQ!$I4),0) -> 35720 | BJ4: =IF(ISNUMBER(InfoQ!$H4),DATE(YEAR(BJ$1),MONTH(BJ$1)+InfoQ!$H4,InfoQ!$I4),0) -> 35812 | BM4: =IF(ISNUMBER(InfoQ!$H4),DATE(YEAR(BM$1),MONTH(BM$1)+InfoQ!$H4,InfoQ!$I4),0) -> 35902 | BP4: =IF(ISNUMBER(InfoQ!$H4),DATE(YEAR(BP$1),MONTH(BP$1)+InfoQ!$H4,InfoQ!$I4),0) -> 35993 | BS4: =IF(ISNUMBER(InfoQ!$H4),DATE(YEAR(BS$1),MONTH(BS$1)+InfoQ!$H4,InfoQ!$I4),0) -> 36085 | BV4: =IF(ISNUMBER(InfoQ!$H4),DATE(YEAR(BV$1),MONTH(BV$1)+InfoQ!$H4,InfoQ!$I4),0) -> 36177 | BY4: =IF(ISNUMBER(InfoQ!$H4),DATE(YEAR(BY$1),MONTH(BY$1)+InfoQ!$H4,InfoQ!$I4),0) -> 36267 | CB4: =IF(ISNUMBER(InfoQ!$H4),DATE(YEAR(CB$1),MONTH(CB$1)+InfoQ!$H4,InfoQ!$I4),0) -> 36358 | CE4: =IF(ISNUMBER(InfoQ!$H4),DATE(YEAR(CE$1),MONTH(CE$1)+InfoQ!$H4,InfoQ!$I4),0) -> 36450 | CH4: =IF(ISNUMBER(InfoQ!$H4),DATE(YEAR(CH$1),MONTH(CH$1)+InfoQ!$H4,InfoQ!$I4),0) -> 36542 | CK4: =IF(ISNUMBER(InfoQ!$H4),DATE(YEAR(CK$1),MONTH(CK$1)+InfoQ!$H4,InfoQ!$I4),0) -> 36633 | CN4: =IF(ISNUMBER(InfoQ!$H4),DATE(YEAR(CN$1),MONTH(CN$1)+InfoQ!$H4,InfoQ!$I4),0) -> 36724 | CQ4: =IF(ISNUMBER(InfoQ!$H4),DATE(YEAR(CQ$1),MONTH(CQ$1)+InfoQ!$H4,InfoQ!$I4),0) -> 36816 | CT4: =IF(ISNUMBER(InfoQ!$H4),DATE(YEAR(CT$1),MONTH(CT$1)+InfoQ!$H4,InfoQ!$I4),0) -> 36908 | CW4: =IF(ISNUMBER(InfoQ!$H4),DATE(YEAR(CW$1),MONTH(CW$1)+InfoQ!$H4,InfoQ!$I4),0) -> 36998 | CZ4: =IF(ISNUMBER(InfoQ!$H4),DATE(YEAR(CZ$1),MONTH(CZ$1)+InfoQ!$H4,InfoQ!$I4),0) -> 37089 | DC4: =IF(ISNUMBER(InfoQ!$H4),DATE(YEAR(DC$1),MONTH(DC$1)+InfoQ!$H4,InfoQ!$I4),0) -> 37181 | DF4: =IF(ISNUMBER(InfoQ!$H4),DATE(YEAR(DF$1),MONTH(DF$1)+InfoQ!$H4,InfoQ!$I4),0) -> 37273 | DI4: =IF(ISNUMBER(InfoQ!$H4),DATE(YEAR(DI$1),MONTH(DI$1)+InfoQ!$H4,InfoQ!$I4),0) -> 37363 | DL4: =IF(ISNUMBER(InfoQ!$H4),DATE(YEAR(DL$1),MONTH(DL$1)+InfoQ!$H4,InfoQ!$I4),0) -> 37454 | DO4: =IF(ISNUMBER(InfoQ!$H4),DATE(YEAR(DO$1),MONTH(DO$1)+InfoQ!$H4,InfoQ!$I4),0) -> 37546 | DR4: =IF(ISNUMBER(InfoQ!$H4),DATE(YEAR(DR$1),MONTH(DR$1)+InfoQ!$H4,InfoQ!$I4),0) -> 37638 | DU4: =IF(ISNUMBER(InfoQ!$H4),DATE(YEAR(DU$1),MONTH(DU$1)+InfoQ!$H4,InfoQ!$I4),0) -> 37728 | DX4: =IF(ISNUMBER(InfoQ!$H4),DATE(YEAR(DX$1),MONTH(DX$1)+InfoQ!$H4,InfoQ!$I4),0) -> 37819 | EA4: =IF(ISNUMBER(InfoQ!$H4),DATE(YEAR(EA$1),MONTH(EA$1)+InfoQ!$H4,InfoQ!$I4),0) -> 37911 | ED4: =IF(ISNUMBER(InfoQ!$H4),DATE(YEAR(ED$1),MONTH(ED$1)+InfoQ!$H4,InfoQ!$I4),0) -> 38003 | EG4: =IF(ISNUMBER(InfoQ!$H4),DATE(YEAR(EG$1),MONTH(EG$1)+InfoQ!$H4,InfoQ!$I4),0) -> 38094 | EJ4: =IF(ISNUMBER(InfoQ!$H4),DATE(YEAR(EJ$1),MONTH(EJ$1)+InfoQ!$H4,InfoQ!$I4),0) -> 38185 | EM4: =IF(ISNUMBER(InfoQ!$H4),DATE(YEAR(EM$1),MONTH(EM$1)+InfoQ!$H4,InfoQ!$I4),0) -> 38277 | EP4: =IF(ISNUMBER(InfoQ!$H4),DATE(YEAR(EP$1),MONTH(EP$1)+InfoQ!$H4,InfoQ!$I4),0) -> 38369 | ES4: =IF(ISNUMBER(InfoQ!$H4),DATE(YEAR(ES$1),MONTH(ES$1)+InfoQ!$H4,InfoQ!$I4),0) -> 38459 | EV4: =IF(ISNUMBER(InfoQ!$H4),DATE(YEAR(EV$1),MONTH(EV$1)+InfoQ!$H4,InfoQ!$I4),0) -> 38550 | EY4: =IF(ISNUMBER(InfoQ!$H4),DATE(YEAR(EY$1),MONTH(EY$1)+InfoQ!$H4,InfoQ!$I4),0) -> 38642 | FB4: =IF(ISNUMBER(InfoQ!$H4),DATE(YEAR(FB$1),MONTH(FB$1)+InfoQ!$H4,InfoQ!$I4),0) -> 38734 | FE4: =IF(ISNUMBER(InfoQ!$H4),DATE(YEAR(FE$1),MONTH(FE$1)+InfoQ!$H4,InfoQ!$I4),0) -> 38824 | FH4: =IF(ISNUMBER(InfoQ!$H4),DATE(YEAR(FH$1),MONTH(FH$1)+InfoQ!$H4,InfoQ!$I4),0) -> 38915 | FK4: =IF(ISNUMBER(InfoQ!$H4),DATE(YEAR(FK$1),MONTH(FK$1)+InfoQ!$H4,InfoQ!$I4),0) -> 39007 | FN4: =IF(ISNUMBER(InfoQ!$H4),DATE(YEAR(FN$1),MONTH(FN$1)+InfoQ!$H4,InfoQ!$I4),0) -> 39099 | FQ4: =IF(ISNUMBER(InfoQ!$H4),DATE(YEAR(FQ$1),MONTH(FQ$1)+InfoQ!$H4,InfoQ!$I4),0) -> 39189 | FT4: =IF(ISNUMBER(InfoQ!$H4),DATE(YEAR(FT$1),MONTH(FT$1)+InfoQ!$H4,InfoQ!$I4),0) -> 39280 | FW4: =IF(ISNUMBER(InfoQ!$H4),DATE(YEAR(FW$1),MONTH(FW$1)+InfoQ!$H4,InfoQ!$I4),0) -> 39372 | FZ4: =IF(ISNUMBER(InfoQ!$H4),DATE(YEAR(FZ$1),MONTH(FZ$1)+InfoQ!$H4,InfoQ!$I4),0) -> 39464 | GC4: =IF(ISNUMBER(InfoQ!$H4),DATE(YEAR(GC$1),MONTH(GC$1)+InfoQ!$H4,InfoQ!$I4),0) -> 39555 | GF4: =IF(ISNUMBER(InfoQ!$H4),DATE(YEAR(GF$1),MONTH(GF$1)+InfoQ!$H4,InfoQ!$I4),0) -> 39646 | GI4: =IF(ISNUMBER(InfoQ!$H4),DATE(YEAR(GI$1),MONTH(GI$1)+InfoQ!$H4,InfoQ!$I4),0) -> 39738 | GL4: =IF(ISNUMBER(InfoQ!$H4),DATE(YEAR(GL$1),MONTH(GL$1)+InfoQ!$H4,InfoQ!$I4),0) -> 39830 | GO4: =IF(ISNUMBER(InfoQ!$H4),DATE(YEAR(GO$1),MONTH(GO$1)+InfoQ!$H4,InfoQ!$I4),0) -> 39920 | GR4: =IF(ISNUMBER(InfoQ!$H4),DATE(YEAR(GR$1),MONTH(GR$1)+InfoQ!$H4,InfoQ!$I4),0) -> 40011 | GU4: =IF(ISNUMBER(InfoQ!$H4),DATE(YEAR(GU$1),MONTH(GU$1)+InfoQ!$H4,InfoQ!$I4),0) -> 40103 | GX4: =IF(ISNUMBER(InfoQ!$H4),DATE(YEAR(GX$1),MONTH(GX$1)+InfoQ!$H4,InfoQ!$I4),0) -> 40195 | HA4: =IF(ISNUMBER(InfoQ!$H4),DATE(YEAR(HA$1),MONTH(HA$1)+InfoQ!$H4,InfoQ!$I4),0) -> 40285 | HD4: =IF(ISNUMBER(InfoQ!$H4),DATE(YEAR(HD$1),MONTH(HD$1)+InfoQ!$H4,InfoQ!$I4),0) -> 40376 | HG4: =IF(ISNUMBER(InfoQ!$H4),DATE(YEAR(HG$1),MONTH(HG$1)+InfoQ!$H4,InfoQ!$I4),0) -> 40468 | HJ4: =IF(ISNUMBER(InfoQ!$H4),DATE(YEAR(HJ$1),MONTH(HJ$1)+InfoQ!$H4,InfoQ!$I4),0) -> 40560 | HM4: =IF(ISNUMBER(InfoQ!$H4),DATE(YEAR(HM$1),MONTH(HM$1)+InfoQ!$H4,InfoQ!$I4),0) -> 40650 | HP4: =IF(ISNUMBER(InfoQ!$H4),DATE(YEAR(HP$1),MONTH(HP$1)+InfoQ!$H4,InfoQ!$I4),0) -> 40741 | HS4: =IF(ISNUMBER(InfoQ!$H4),DATE(YEAR(HS$1),MONTH(HS$1)+InfoQ!$H4,InfoQ!$I4),0) -> 40833 | HV4: =IF(ISNUMBER(InfoQ!$H4),DATE(YEAR(HV$1),MONTH(HV$1)+InfoQ!$H4,InfoQ!$I4),0) -> 40925 | HY4: =IF(ISNUMBER(InfoQ!$H4),DATE(YEAR(HY$1),MONTH(HY$1)+InfoQ!$H4,InfoQ!$I4),0) -> 41016 | IB4: =IF(ISNUMBER(InfoQ!$H4),DATE(YEAR(IB$1),MONTH(IB$1)+InfoQ!$H4,InfoQ!$I4),0) -> 41107 | IE4: =IF(ISNUMBER(InfoQ!$H4),DATE(YEAR(IE$1),MONTH(IE$1)+InfoQ!$H4,InfoQ!$I4),0) -> 41199 | IH4: =IF(ISNUMBER(InfoQ!$H4),DATE(YEAR(IH$1),MONTH(IH$1)+InfoQ!$H4,InfoQ!$I4),0) -> 41291 | IK4: =IF(ISNUMBER(InfoQ!$H4),DATE(YEAR(IK$1),MONTH(IK$1)+InfoQ!$H4,InfoQ!$I4),0) -> 41381 | IN4: =IF(ISNUMBER(InfoQ!$H4),DATE(YEAR(IN$1),MONTH(IN$1)+InfoQ!$H4,InfoQ!$I4),0) -> 41472 | IQ4: =IF(ISNUMBER(InfoQ!$H4),DATE(YEAR(IQ$1),MONTH(IQ$1)+InfoQ!$H4,InfoQ!$I4),0) -> 41564 | IT4: =IF(ISNUMBER(InfoQ!$H4),DATE(YEAR(IT$1),MONTH(IT$1)+InfoQ!$H4,InfoQ!$I4),0) -> 41656 | IW4: =IF(ISNUMBER(InfoQ!$H4),DATE(YEAR(IW$1),MONTH(IW$1)+InfoQ!$H4,InfoQ!$I4),0) -> 41746 | IZ4: =IF(ISNUMBER(InfoQ!$H4),DATE(YEAR(IZ$1),MONTH(IZ$1)+InfoQ!$H4,InfoQ!$I4),0) -> 41837 | JC4: =IF(ISNUMBER(InfoQ!$H4),DATE(YEAR(JC$1),MONTH(JC$1)+InfoQ!$H4,InfoQ!$I4),0) -> 41929 | JF4: =IF(ISNUMBER(InfoQ!$H4),DATE(YEAR(JF$1),MONTH(JF$1)+InfoQ!$H4,InfoQ!$I4),0) -> 42021 | JI4: =IF(ISNUMBER(InfoQ!$H4),DATE(YEAR(JI$1),MONTH(JI$1)+InfoQ!$H4,InfoQ!$I4),0) -> 42111 | JL4: =IF(ISNUMBER(InfoQ!$H4),DATE(YEAR(JL$1),MONTH(JL$1)+InfoQ!$H4,InfoQ!$I4),0) -> 42202 | JO4: =IF(ISNUMBER(InfoQ!$H4),DATE(YEAR(JO$1),MONTH(JO$1)+InfoQ!$H4,InfoQ!$I4),0) -> 42294 | JR4: =IF(ISNUMBER(InfoQ!$H4),DATE(YEAR(JR$1),MONTH(JR$1)+InfoQ!$H4,InfoQ!$I4),0) -> 42386 | JU4: =IF(ISNUMBER(InfoQ!$H4),DATE(YEAR(JU$1),MONTH(JU$1)+InfoQ!$H4,InfoQ!$I4),0) -> 42477 | JX4: =IF(ISNUMBER(InfoQ!$H4),DATE(YEAR(JX$1),MONTH(JX$1)+InfoQ!$H4,InfoQ!$I4),0) -> 42568 | KA4: =IF(ISNUMBER(InfoQ!$H4),DATE(YEAR(KA$1),MONTH(KA$1)+InfoQ!$H4,InfoQ!$I4),0) -> 42660 | KD4: =IF(ISNUMBER(InfoQ!$H4),DATE(YEAR(KD$1),MONTH(KD$1)+InfoQ!$H4,InfoQ!$I4),0) -> 42752 | KG4: =IF(ISNUMBER(InfoQ!$H4),DATE(YEAR(KG$1),MONTH(KG$1)+InfoQ!$H4,InfoQ!$I4),0) -> 42842 | KJ4: =IF(ISNUMBER(InfoQ!$H4),DATE(YEAR(KJ$1),MONTH(KJ$1)+InfoQ!$H4,InfoQ!$I4),0) -> 42933 | KM4: =IF(ISNUMBER(InfoQ!$H4),DATE(YEAR(KM$1),MONTH(KM$1)+InfoQ!$H4,InfoQ!$I4),0) -> 43025 | KP4: =IF(ISNUMBER(InfoQ!$H4),DATE(YEAR(KP$1),MONTH(KP$1)+InfoQ!$H4,InfoQ!$I4),0) -> 43117 | KS4: =IF(ISNUMBER(InfoQ!$H4),DATE(YEAR(KS$1),MONTH(KS$1)+InfoQ!$H4,InfoQ!$I4),0) -> 43207 | KV4: =IF(ISNUMBER(InfoQ!$H4),DATE(YEAR(KV$1),MONTH(KV$1)+InfoQ!$H4,InfoQ!$I4),0) -> 43298 | KY4: =IF(ISNUMBER(InfoQ!$H4),DATE(YEAR(KY$1),MONTH(KY$1)+InfoQ!$H4,InfoQ!$I4),0) -> 43390 | LB4: =IF(ISNUMBER(InfoQ!$H4),DATE(YEAR(LB$1),MONTH(LB$1)+InfoQ!$H4,InfoQ!$I4),0) -> 43482 | LE4: =IF(ISNUMBER(InfoQ!$H4),DATE(YEAR(LE$1),MONTH(LE$1)+InfoQ!$H4,InfoQ!$I4),0) -> 43572 | LH4: =IF(ISNUMBER(InfoQ!$H4),DATE(YEAR(LH$1),MONTH(LH$1)+InfoQ!$H4,InfoQ!$I4),0) -> 43663 | LK4: =IF(ISNUMBER(InfoQ!$H4),DATE(YEAR(LK$1),MONTH(LK$1)+InfoQ!$H4,InfoQ!$I4),0) -> 43755 | LN4: =IF(ISNUMBER(InfoQ!$H4),DATE(YEAR(LN$1),MONTH(LN$1)+InfoQ!$H4,InfoQ!$I4),0) -> 43847 | LQ4: =IF(ISNUMBER(InfoQ!$H4),DATE(YEAR(LQ$1),MONTH(LQ$1)+InfoQ!$H4,InfoQ!$I4),0) -> 43938 | LT4: =IF(ISNUMBER(InfoQ!$H4),DATE(YEAR(LT$1),MONTH(LT$1)+InfoQ!$H4,InfoQ!$I4),0) -> 44029 | LW4: =IF(ISNUMBER(InfoQ!$H4),DATE(YEAR(LW$1),MONTH(LW$1)+InfoQ!$H4,InfoQ!$I4),0) -> 44121 | LZ4: =IF(ISNUMBER(InfoQ!$H4),DATE(YEAR(LZ$1),MONTH(LZ$1)+InfoQ!$H4,InfoQ!$I4),0) -> 44213 | MC4: =IF(ISNUMBER(InfoQ!$H4),DATE(YEAR(MC$1),MONTH(MC$1)+InfoQ!$H4,InfoQ!$I4),0) -> 44303 | MF4: =IF(ISNUMBER(InfoQ!$H4),DATE(YEAR(MF$1),MONTH(MF$1)+InfoQ!$H4,InfoQ!$I4),0) -> 44394 | MI4: =IF(ISNUMBER(InfoQ!$H4),DATE(YEAR(MI$1),MONTH(MI$1)+InfoQ!$H4,InfoQ!$I4),0) -> 44486 | ML4: =IF(ISNUMBER(InfoQ!$H4),DATE(YEAR(ML$1),MONTH(ML$1)+InfoQ!$H4,InfoQ!$I4),0) -> 44578 | MO4: =IF(ISNUMBER(InfoQ!$H4),DATE(YEAR(MO$1),MONTH(MO$1)+InfoQ!$H4,InfoQ!$I4),0) -> 44668 | MR4: =IF(ISNUMBER(InfoQ!$H4),DATE(YEAR(MR$1),MONTH(MR$1)+InfoQ!$H4,InfoQ!$I4),0) -> 44759 | MU4: =IF(ISNUMBER(InfoQ!$H4),DATE(YEAR(MU$1),MONTH(MU$1)+InfoQ!$H4,InfoQ!$I4),0) -> 44851 | MX4: =IF(ISNUMBER(InfoQ!$H4),DATE(YEAR(MX$1),MONTH(MX$1)+InfoQ!$H4,InfoQ!$I4),0) -> 44943 | NA4: =IF(ISNUMBER(InfoQ!$H4),DATE(YEAR(NA$1),MONTH(NA$1)+InfoQ!$H4,InfoQ!$I4),0) -> 45033 | ND4: =IF(ISNUMBER(InfoQ!$H4),DATE(YEAR(ND$1),MONTH(ND$1)+InfoQ!$H4,InfoQ!$I4),0) -> 45124 | NG4: =IF(ISNUMBER(InfoQ!$H4),DATE(YEAR(NG$1),MONTH(NG$1)+InfoQ!$H4,InfoQ!$I4),0) -> 45216 | NJ4: =IF(ISNUMBER(InfoQ!$H4),DATE(YEAR(NJ$1),MONTH(NJ$1)+InfoQ!$H4,InfoQ!$I4),0) -> 45308 | NM4: =IF(ISNUMBER(InfoQ!$H4),DATE(YEAR(NM$1),MONTH(NM$1)+InfoQ!$H4,InfoQ!$I4),0) -> 45399 | NP4: =IF(ISNUMBER(InfoQ!$H4),DATE(YEAR(NP$1),MONTH(NP$1)+InfoQ!$H4,InfoQ!$I4),0) -> 45490 | NS4: =IF(ISNUMBER(InfoQ!$H4),DATE(YEAR(NS$1),MONTH(NS$1)+InfoQ!$H4,InfoQ!$I4),0) -> 45582 | NV4: =IF(ISNUMBER(InfoQ!$H4),DATE(YEAR(NV$1),MONTH(NV$1)+InfoQ!$H4,InfoQ!$I4),0) -> 45674 | NY4: =IF(ISNUMBER(InfoQ!$H4),DATE(YEAR(NY$1),MONTH(NY$1)+InfoQ!$H4,InfoQ!$I4),0) -> 45764 | OB4: =IF(ISNUMBER(InfoQ!$H4),DATE(YEAR(OB$1),MONTH(OB$1)+InfoQ!$H4,InfoQ!$I4),0) -> 45855 | OE4: =IF(ISNUMBER(InfoQ!$H4),DATE(YEAR(OE$1),MONTH(OE$1)+InfoQ!$H4,InfoQ!$I4),0) -> 45947 | OH4: =IF(ISNUMBER(InfoQ!$H4),DATE(YEAR(OH$1),MONTH(OH$1)+InfoQ!$H4,InfoQ!$I4),0) -> 46039 | OK4: =IF(ISNUMBER(InfoQ!$H4),DATE(YEAR(OK$1),MONTH(OK$1)+InfoQ!$H4,InfoQ!$I4),0) -> 46129 | ON4: =IF(ISNUMBER(InfoQ!$H4),DATE(YEAR(ON$1),MONTH(ON$1)+InfoQ!$H4,InfoQ!$I4),0) -> 46220 | OQ4: =IF(ISNUMBER(InfoQ!$H4),DATE(YEAR(OQ$1),MONTH(OQ$1)+InfoQ!$H4,InfoQ!$I4),0) -> 46312 | OT4: =IF(ISNUMBER(InfoQ!$H4),DATE(YEAR(OT$1),MONTH(OT$1)+InfoQ!$H4,InfoQ!$I4),0) -> 46404
A5: =InfoM!A2 -> Man_PMI_EM | B5: =InfoM!G2 -> 1 | C5: =DATE(YEAR(C$1),MONTH(C$1)+InfoM!$H2,InfoM!$I2) -> 34001 | D5: =DATE(YEAR(D$1),MONTH(D$1)+InfoM!$H2,InfoM!$I2) -> 34029 | E5: =DATE(YEAR(E$1),MONTH(E$1)+InfoM!$H2,InfoM!$I2) -> 34060 | F5: =DATE(YEAR(F$1),MONTH(F$1)+InfoM!$H2,InfoM!$I2) -> 34090 | G5: =DATE(YEAR(G$1),MONTH(G$1)+InfoM!$H2,InfoM!$I2) -> 34121 | H5: =DATE(YEAR(H$1),MONTH(H$1)+InfoM!$H2,InfoM!$I2) -> 34151 | I5: =DATE(YEAR(I$1),MONTH(I$1)+InfoM!$H2,InfoM!$I2) -> 34182 | J5: =DATE(YEAR(J$1),MONTH(J$1)+InfoM!$H2,InfoM!$I2) -> 34213 | ... OT5: =DATE(YEAR(OT$1),MONTH(OT$1)+InfoM!$H2,InfoM!$I2) -> 46388
A6: =InfoM!A3 -> M2 | B6: =InfoM!G3 -> 1 | C6: =DATE(YEAR(C$1),MONTH(C$1)+InfoM!$H3,InfoM!$I3) -> 34021 | D6: =DATE(YEAR(D$1),MONTH(D$1)+InfoM!$H3,InfoM!$I3) -> 34049 | E6: =DATE(YEAR(E$1),MONTH(E$1)+InfoM!$H3,InfoM!$I3) -> 34080 | F6: =DATE(YEAR(F$1),MONTH(F$1)+InfoM!$H3,InfoM!$I3) -> 34110 | G6: =DATE(YEAR(G$1),MONTH(G$1)+InfoM!$H3,InfoM!$I3) -> 34141 | H6: =DATE(YEAR(H$1),MONTH(H$1)+InfoM!$H3,InfoM!$I3) -> 34171 | I6: =DATE(YEAR(I$1),MONTH(I$1)+InfoM!$H3,InfoM!$I3) -> 34202 | J6: =DATE(YEAR(J$1),MONTH(J$1)+InfoM!$H3,InfoM!$I3) -> 34233 | ... OT6: =DATE(YEAR(OT$1),MONTH(OT$1)+InfoM!$H3,InfoM!$I3) -> 46408
A7: =InfoM!A4 -> Car_sales | B7: =InfoM!G4 -> 1 | C7: =DATE(YEAR(C$1),MONTH(C$1)+InfoM!$H4,InfoM!$I4) -> 34015 | D7: =DATE(YEAR(D$1),MONTH(D$1)+InfoM!$H4,InfoM!$I4) -> 34043 | E7: =DATE(YEAR(E$1),MONTH(E$1)+InfoM!$H4,InfoM!$I4) -> 34074 | F7: =DATE(YEAR(F$1),MONTH(F$1)+InfoM!$H4,InfoM!$I4) -> 34104 | G7: =DATE(YEAR(G$1),MONTH(G$1)+InfoM!$H4,InfoM!$I4) -> 34135 | H7: =DATE(YEAR(H$1),MONTH(H$1)+InfoM!$H4,InfoM!$I4) -> 34165 | I7: =DATE(YEAR(I$1),MONTH(I$1)+InfoM!$H4,InfoM!$I4) -> 34196 | J7: =DATE(YEAR(J$1),MONTH(J$1)+InfoM!$H4,InfoM!$I4) -> 34227 | ... OT7: =DATE(YEAR(OT$1),MONTH(OT$1)+InfoM!$H4,InfoM!$I4) -> 46402
A8: =InfoM!A5 -> Cement | B8: =InfoM!G5 -> 1 | C8: =DATE(YEAR(C$1),MONTH(C$1)+InfoM!$H5,InfoM!$I5) -> 34026 | D8: =DATE(YEAR(D$1),MONTH(D$1)+InfoM!$H5,InfoM!$I5) -> 34054 | E8: =DATE(YEAR(E$1),MONTH(E$1)+InfoM!$H5,InfoM!$I5) -> 34085 | F8: =DATE(YEAR(F$1),MONTH(F$1)+InfoM!$H5,InfoM!$I5) -> 34115 | G8: =DATE(YEAR(G$1),MONTH(G$1)+InfoM!$H5,InfoM!$I5) -> 34146 | H8: =DATE(YEAR(H$1),MONTH(H$1)+InfoM!$H5,InfoM!$I5) -> 34176 | I8: =DATE(YEAR(I$1),MONTH(I$1)+InfoM!$H5,InfoM!$I5) -> 34207 | J8: =DATE(YEAR(J$1),MONTH(J$1)+InfoM!$H5,InfoM!$I5) -> 34238 | ... OT8: =DATE(YEAR(OT$1),MONTH(OT$1)+InfoM!$H5,InfoM!$I5) -> 46413
A9: =InfoM!A6 -> Export | B9: =InfoM!G6 -> 1 | C9: =DATE(YEAR(C$1),MONTH(C$1)+InfoM!$H6,InfoM!$I6) -> 34029 | D9: =DATE(YEAR(D$1),MONTH(D$1)+InfoM!$H6,InfoM!$I6) -> 34060 | E9: =DATE(YEAR(E$1),MONTH(E$1)+InfoM!$H6,InfoM!$I6) -> 34090 | F9: =DATE(YEAR(F$1),MONTH(F$1)+InfoM!$H6,InfoM!$I6) -> 34121 | G9: =DATE(YEAR(G$1),MONTH(G$1)+InfoM!$H6,InfoM!$I6) -> 34151 | H9: =DATE(YEAR(H$1),MONTH(H$1)+InfoM!$H6,InfoM!$I6) -> 34182 | I9: =DATE(YEAR(I$1),MONTH(I$1)+InfoM!$H6,InfoM!$I6) -> 34213 | J9: =DATE(YEAR(J$1),MONTH(J$1)+InfoM!$H6,InfoM!$I6) -> 34243 | ... OT9: =DATE(YEAR(OT$1),MONTH(OT$1)+InfoM!$H6,InfoM!$I6) -> 46419
A10: =InfoM!A7 -> M_con_goods | B10: =InfoM!G7 -> 1 | C10: =DATE(YEAR(C$1),MONTH(C$1)+InfoM!$H7,InfoM!$I7) -> 34029 | D10: =DATE(YEAR(D$1),MONTH(D$1)+InfoM!$H7,InfoM!$I7) -> 34060 | E10: =DATE(YEAR(E$1),MONTH(E$1)+InfoM!$H7,InfoM!$I7) -> 34090 | F10: =DATE(YEAR(F$1),MONTH(F$1)+InfoM!$H7,InfoM!$I7) -> 34121 | G10: =DATE(YEAR(G$1),MONTH(G$1)+InfoM!$H7,InfoM!$I7) -> 34151 | H10: =DATE(YEAR(H$1),MONTH(H$1)+InfoM!$H7,InfoM!$I7) -> 34182 | I10: =DATE(YEAR(I$1),MONTH(I$1)+InfoM!$H7,InfoM!$I7) -> 34213 | J10: =DATE(YEAR(J$1),MONTH(J$1)+InfoM!$H7,InfoM!$I7) -> 34243 | ... OT10: =DATE(YEAR(OT$1),MONTH(OT$1)+InfoM!$H7,InfoM!$I7) -> 46419
A11: =InfoM!A8 -> M_cap_goods | B11: =InfoM!G8 -> 1 | C11: =DATE(YEAR(C$1),MONTH(C$1)+InfoM!$H8,InfoM!$I8) -> 34029 | D11: =DATE(YEAR(D$1),MONTH(D$1)+InfoM!$H8,InfoM!$I8) -> 34060 | E11: =DATE(YEAR(E$1),MONTH(E$1)+InfoM!$H8,InfoM!$I8) -> 34090 | F11: =DATE(YEAR(F$1),MONTH(F$1)+InfoM!$H8,InfoM!$I8) -> 34121 | G11: =DATE(YEAR(G$1),MONTH(G$1)+InfoM!$H8,InfoM!$I8) -> 34151 | H11: =DATE(YEAR(H$1),MONTH(H$1)+InfoM!$H8,InfoM!$I8) -> 34182 | I11: =DATE(YEAR(I$1),MONTH(I$1)+InfoM!$H8,InfoM!$I8) -> 34213 | J11: =DATE(YEAR(J$1),MONTH(J$1)+InfoM!$H8,InfoM!$I8) -> 34243 | ... OT11: =DATE(YEAR(OT$1),MONTH(OT$1)+InfoM!$H8,InfoM!$I8) -> 46419
A12: =InfoM!A9 -> M_raw_mat | B12: =InfoM!G9 -> 1 | C12: =DATE(YEAR(C$1),MONTH(C$1)+InfoM!$H9,InfoM!$I9) -> 34029 | D12: =DATE(YEAR(D$1),MONTH(D$1)+InfoM!$H9,InfoM!$I9) -> 34060 | E12: =DATE(YEAR(E$1),MONTH(E$1)+InfoM!$H9,InfoM!$I9) -> 34090 | F12: =DATE(YEAR(F$1),MONTH(F$1)+InfoM!$H9,InfoM!$I9) -> 34121 | G12: =DATE(YEAR(G$1),MONTH(G$1)+InfoM!$H9,InfoM!$I9) -> 34151 | H12: =DATE(YEAR(H$1),MONTH(H$1)+InfoM!$H9,InfoM!$I9) -> 34182 | I12: =DATE(YEAR(I$1),MONTH(I$1)+InfoM!$H9,InfoM!$I9) -> 34213 | J12: =DATE(YEAR(J$1),MONTH(J$1)+InfoM!$H9,InfoM!$I9) -> 34243 | ... OT12: =DATE(YEAR(OT$1),MONTH(OT$1)+InfoM!$H9,InfoM!$I9) -> 46419
A13: =InfoM!A10 -> Inflation | B13: =InfoM!G10 -> 1 | C13: =DATE(YEAR(C$1),MONTH(C$1)+InfoM!$H10,InfoM!$I10) -> 34001 | D13: =DATE(YEAR(D$1),MONTH(D$1)+InfoM!$H10,InfoM!$I10) -> 34029 | E13: =DATE(YEAR(E$1),MONTH(E$1)+InfoM!$H10,InfoM!$I10) -> 34060 | F13: =DATE(YEAR(F$1),MONTH(F$1)+InfoM!$H10,InfoM!$I10) -> 34090 | G13: =DATE(YEAR(G$1),MONTH(G$1)+InfoM!$H10,InfoM!$I10) -> 34121 | H13: =DATE(YEAR(H$1),MONTH(H$1)+InfoM!$H10,InfoM!$I10) -> 34151 | I13: =DATE(YEAR(I$1),MONTH(I$1)+InfoM!$H10,InfoM!$I10) -> 34182 | J13: =DATE(YEAR(J$1),MONTH(J$1)+InfoM!$H10,InfoM!$I10) -> 34213 | ... OT13: =DATE(YEAR(OT$1),MONTH(OT$1)+InfoM!$H10,InfoM!$I10) -> 46388
A14: =InfoM!A11 -> Forex | B14: =InfoM!G11 -> 0 | C14: =DATE(YEAR(C$1),MONTH(C$1)+InfoM!$H11,InfoM!$I11) -> 34001 | D14: =DATE(YEAR(D$1),MONTH(D$1)+InfoM!$H11,InfoM!$I11) -> 34029 | E14: =DATE(YEAR(E$1),MONTH(E$1)+InfoM!$H11,InfoM!$I11) -> 34060 | F14: =DATE(YEAR(F$1),MONTH(F$1)+InfoM!$H11,InfoM!$I11) -> 34090 | G14: =DATE(YEAR(G$1),MONTH(G$1)+InfoM!$H11,InfoM!$I11) -> 34121 | H14: =DATE(YEAR(H$1),MONTH(H$1)+InfoM!$H11,InfoM!$I11) -> 34151 | I14: =DATE(YEAR(I$1),MONTH(I$1)+InfoM!$H11,InfoM!$I11) -> 34182 | J14: =DATE(YEAR(J$1),MONTH(J$1)+InfoM!$H11,InfoM!$I11) -> 34213 | ... OT14: =DATE(YEAR(OT$1),MONTH(OT$1)+InfoM!$H11,InfoM!$I11) -> 46388
A15: =InfoM!A12 -> Policy_rate | B15: =InfoM!G12 -> 1 | C15: =DATE(YEAR(C$1),MONTH(C$1)+InfoM!$H12,InfoM!$I12) -> 34018 | D15: =DATE(YEAR(D$1),MONTH(D$1)+InfoM!$H12,InfoM!$I12) -> 34046 | E15: =DATE(YEAR(E$1),MONTH(E$1)+InfoM!$H12,InfoM!$I12) -> 34077 | F15: =DATE(YEAR(F$1),MONTH(F$1)+InfoM!$H12,InfoM!$I12) -> 34107 | G15: =DATE(YEAR(G$1),MONTH(G$1)+InfoM!$H12,InfoM!$I12) -> 34138 | H15: =DATE(YEAR(H$1),MONTH(H$1)+InfoM!$H12,InfoM!$I12) -> 34168 | I15: =DATE(YEAR(I$1),MONTH(I$1)+InfoM!$H12,InfoM!$I12) -> 34199 | J15: =DATE(YEAR(J$1),MONTH(J$1)+InfoM!$H12,InfoM!$I12) -> 34230 | ... OT15: =DATE(YEAR(OT$1),MONTH(OT$1)+InfoM!$H12,InfoM!$I12) -> 46405
B16: =SUM(B2:B15) -> 12
